<PAMDataset>
  <PAMRasterBand band="1">
    <Metadata>
      <MDI key="STATISTICS_MAXIMUM">220.41058726089</MDI>
      <MDI key="STATISTICS_MEAN">-9999</MDI>
      <MDI key="STATISTICS_MINIMUM">4.4275949603348</MDI>
      <MDI key="STATISTICS_STDDEV">-9999</MDI>
    </Metadata>
  </PAMRasterBand>
  <PAMRasterBand band="2">
    <Metadata>
      <MDI key="STATISTICS_MAXIMUM">287.32141783374</MDI>
      <MDI key="STATISTICS_MEAN">-9999</MDI>
      <MDI key="STATISTICS_MINIMUM">43.62489188883</MDI>
      <MDI key="STATISTICS_STDDEV">-9999</MDI>
    </Metadata>
  </PAMRasterBand>
  <PAMRasterBand band="3">
    <Metadata>
      <MDI key="STATISTICS_MAXIMUM">238.67719774059</MDI>
      <MDI key="STATISTICS_MEAN">-9999</MDI>
      <MDI key="STATISTICS_MINIMUM">-2.0645442513372</MDI>
      <MDI key="STATISTICS_STDDEV">-9999</MDI>
    </Metadata>
  </PAMRasterBand>
  <PAMRasterBand band="4">
    <Metadata>
      <MDI key="STATISTICS_MAXIMUM">148.1700290269</MDI>
      <MDI key="STATISTICS_MEAN">-9999</MDI>
      <MDI key="STATISTICS_MINIMUM">-22.26310951345</MDI>
      <MDI key="STATISTICS_STDDEV">-9999</MDI>
    </Metadata>
  </PAMRasterBand>
  <PAMRasterBand band="5">
    <Metadata>
      <MDI key="STATISTICS_MAXIMUM">156.0998556865</MDI>
      <MDI key="STATISTICS_MEAN">-9999</MDI>
      <MDI key="STATISTICS_MINIMUM">-18.484340563301</MDI>
      <MDI key="STATISTICS_STDDEV">-9999</MDI>
    </Metadata>
  </PAMRasterBand>
  <PAMRasterBand band="6">
    <Metadata>
      <MDI key="STATISTICS_MAXIMUM">25.620489862365</MDI>
      <MDI key="STATISTICS_MEAN">-9999</MDI>
      <MDI key="STATISTICS_MINIMUM">-1.7905664586205</MDI>
      <MDI key="STATISTICS_STDDEV">-9999</MDI>
    </Metadata>
  </PAMRasterBand>
  <PAMRasterBand band="7">
    <Metadata>
      <MDI key="STATISTICS_MAXIMUM">64.654443778513</MDI>
      <MDI key="STATISTICS_MEAN">-9999</MDI>
      <MDI key="STATISTICS_MINIMUM">-21.453952556367</MDI>
      <MDI key="STATISTICS_STDDEV">-9999</MDI>
    </Metadata>
  </PAMRasterBand>
  <PAMRasterBand band="8">
    <Metadata>
      <MDI key="STATISTICS_MAXIMUM">48.266308332437</MDI>
      <MDI key="STATISTICS_MEAN">-9999</MDI>
      <MDI key="STATISTICS_MINIMUM">-7.6083943257305</MDI>
      <MDI key="STATISTICS_STDDEV">-9999</MDI>
    </Metadata>
  </PAMRasterBand>
  <PAMRasterBand band="9">
    <Metadata>
      <MDI key="STATISTICS_MAXIMUM">70.425360959253</MDI>
      <MDI key="STATISTICS_MEAN">-9999</MDI>
      <MDI key="STATISTICS_MINIMUM">-15.75146467775</MDI>
      <MDI key="STATISTICS_STDDEV">-9999</MDI>
    </Metadata>
  </PAMRasterBand>
  <PAMRasterBand band="10">
    <Metadata>
      <MDI key="STATISTICS_MAXIMUM">216.07243594718</MDI>
      <MDI key="STATISTICS_MEAN">-9999</MDI>
      <MDI key="STATISTICS_MINIMUM">-39.222506763035</MDI>
      <MDI key="STATISTICS_STDDEV">-9999</MDI>
    </Metadata>
  </PAMRasterBand>
  <PAMRasterBand band="11">
    <Metadata>
      <MDI key="STATISTICS_MAXIMUM">207.63147726223</MDI>
      <MDI key="STATISTICS_MEAN">-9999</MDI>
      <MDI key="STATISTICS_MINIMUM">-21.761630913129</MDI>
      <MDI key="STATISTICS_STDDEV">-9999</MDI>
    </Metadata>
  </PAMRasterBand>
  <PAMRasterBand band="12">
    <Metadata>
      <MDI key="STATISTICS_MAXIMUM">306.60403440859</MDI>
      <MDI key="STATISTICS_MEAN">-9999</MDI>
      <MDI key="STATISTICS_MINIMUM">-18.567384107092</MDI>
      <MDI key="STATISTICS_STDDEV">-9999</MDI>
    </Metadata>
  </PAMRasterBand>
  <PAMRasterBand band="13">
    <Metadata>
      <MDI key="STATISTICS_MAXIMUM">205.0000189115</MDI>
      <MDI key="STATISTICS_MEAN">-9999</MDI>
      <MDI key="STATISTICS_MINIMUM">-7.9413849997165</MDI>
      <MDI key="STATISTICS_STDDEV">-9999</MDI>
    </Metadata>
  </PAMRasterBand>
  <PAMRasterBand band="14">
    <Metadata>
      <MDI key="STATISTICS_MAXIMUM">406.87758134538</MDI>
      <MDI key="STATISTICS_MEAN">-9999</MDI>
      <MDI key="STATISTICS_MINIMUM">23.578257948608</MDI>
      <MDI key="STATISTICS_STDDEV">-9999</MDI>
    </Metadata>
  </PAMRasterBand>
  <PAMRasterBand band="15">
    <Metadata>
      <MDI key="STATISTICS_MAXIMUM">395.12890318528</MDI>
      <MDI key="STATISTICS_MEAN">-9999</MDI>
      <MDI key="STATISTICS_MINIMUM">64.719704836794</MDI>
      <MDI key="STATISTICS_STDDEV">-9999</MDI>
    </Metadata>
  </PAMRasterBand>
  <PAMRasterBand band="16">
    <Metadata>
      <MDI key="STATISTICS_MAXIMUM">270.25064697683</MDI>
      <MDI key="STATISTICS_MEAN">-9999</MDI>
      <MDI key="STATISTICS_MINIMUM">-10.555955042454</MDI>
      <MDI key="STATISTICS_STDDEV">-9999</MDI>
    </Metadata>
  </PAMRasterBand>
  <PAMRasterBand band="17">
    <Metadata>
      <MDI key="STATISTICS_MAXIMUM">112.39051278117</MDI>
      <MDI key="STATISTICS_MEAN">-9999</MDI>
      <MDI key="STATISTICS_MINIMUM">-18.469057005171</MDI>
      <MDI key="STATISTICS_STDDEV">-9999</MDI>
    </Metadata>
  </PAMRasterBand>
  <PAMRasterBand band="18">
    <Metadata>
      <MDI key="STATISTICS_MAXIMUM">48.831377898474</MDI>
      <MDI key="STATISTICS_MEAN">-9999</MDI>
      <MDI key="STATISTICS_MINIMUM">-5.3534666935794</MDI>
      <MDI key="STATISTICS_STDDEV">-9999</MDI>
    </Metadata>
  </PAMRasterBand>
  <PAMRasterBand band="19">
    <Metadata>
      <MDI key="STATISTICS_MAXIMUM">24.186541324129</MDI>
      <MDI key="STATISTICS_MEAN">-9999</MDI>
      <MDI key="STATISTICS_MINIMUM">-1.2542410494375</MDI>
      <MDI key="STATISTICS_STDDEV">-9999</MDI>
    </Metadata>
  </PAMRasterBand>
  <PAMRasterBand band="20">
    <Metadata>
      <MDI key="STATISTICS_MAXIMUM">44.6767182512</MDI>
      <MDI key="STATISTICS_MEAN">-9999</MDI>
      <MDI key="STATISTICS_MINIMUM">-4.4318613683221</MDI>
      <MDI key="STATISTICS_STDDEV">-9999</MDI>
    </Metadata>
  </PAMRasterBand>
  <PAMRasterBand band="21">
    <Metadata>
      <MDI key="STATISTICS_MAXIMUM">72.847480175655</MDI>
      <MDI key="STATISTICS_MEAN">-9999</MDI>
      <MDI key="STATISTICS_MINIMUM">-10.602982893677</MDI>
      <MDI key="STATISTICS_STDDEV">-9999</MDI>
    </Metadata>
  </PAMRasterBand>
  <PAMRasterBand band="22">
    <Metadata>
      <MDI key="STATISTICS_MAXIMUM">326.02368081681</MDI>
      <MDI key="STATISTICS_MEAN">-9999</MDI>
      <MDI key="STATISTICS_MINIMUM">-31.337586705317</MDI>
      <MDI key="STATISTICS_STDDEV">-9999</MDI>
    </Metadata>
  </PAMRasterBand>
  <PAMRasterBand band="23">
    <Metadata>
      <MDI key="STATISTICS_MAXIMUM">90.194412952954</MDI>
      <MDI key="STATISTICS_MEAN">-9999</MDI>
      <MDI key="STATISTICS_MINIMUM">-13.737142292832</MDI>
      <MDI key="STATISTICS_STDDEV">-9999</MDI>
    </Metadata>
  </PAMRasterBand>
  <PAMRasterBand band="24">
    <Metadata>
      <MDI key="STATISTICS_MAXIMUM">55.602353937507</MDI>
      <MDI key="STATISTICS_MEAN">-9999</MDI>
      <MDI key="STATISTICS_MINIMUM">-8.4649262208073</MDI>
      <MDI key="STATISTICS_STDDEV">-9999</MDI>
    </Metadata>
  </PAMRasterBand>
  <PAMRasterBand band="25">
    <Metadata>
      <MDI key="STATISTICS_MAXIMUM">183.28987129373</MDI>
      <MDI key="STATISTICS_MEAN">-9999</MDI>
      <MDI key="STATISTICS_MINIMUM">-5.975442631171</MDI>
      <MDI key="STATISTICS_STDDEV">-9999</MDI>
    </Metadata>
  </PAMRasterBand>
  <PAMRasterBand band="26">
    <Metadata>
      <MDI key="STATISTICS_MAXIMUM">270.07182766528</MDI>
      <MDI key="STATISTICS_MEAN">-9999</MDI>
      <MDI key="STATISTICS_MINIMUM">21.697375458849</MDI>
      <MDI key="STATISTICS_STDDEV">-9999</MDI>
    </Metadata>
  </PAMRasterBand>
  <PAMRasterBand band="27">
    <Metadata>
      <MDI key="STATISTICS_MAXIMUM">122.90021629208</MDI>
      <MDI key="STATISTICS_MEAN">-9999</MDI>
      <MDI key="STATISTICS_MINIMUM">0.56636810005082</MDI>
      <MDI key="STATISTICS_STDDEV">-9999</MDI>
    </Metadata>
  </PAMRasterBand>
  <PAMRasterBand band="28">
    <Metadata>
      <MDI key="STATISTICS_MAXIMUM">257.68529450628</MDI>
      <MDI key="STATISTICS_MEAN">-9999</MDI>
      <MDI key="STATISTICS_MINIMUM">13.949990296659</MDI>
      <MDI key="STATISTICS_STDDEV">-9999</MDI>
    </Metadata>
  </PAMRasterBand>
  <PAMRasterBand band="29">
    <Metadata>
      <MDI key="STATISTICS_MAXIMUM">80.264223787216</MDI>
      <MDI key="STATISTICS_MEAN">-9999</MDI>
      <MDI key="STATISTICS_MINIMUM">-12.992281610162</MDI>
      <MDI key="STATISTICS_STDDEV">-9999</MDI>
    </Metadata>
  </PAMRasterBand>
  <PAMRasterBand band="30">
    <Metadata>
      <MDI key="STATISTICS_MAXIMUM">73.040093843511</MDI>
      <MDI key="STATISTICS_MEAN">-9999</MDI>
      <MDI key="STATISTICS_MINIMUM">-7.9190459116679</MDI>
      <MDI key="STATISTICS_STDDEV">-9999</MDI>
    </Metadata>
  </PAMRasterBand>
  <PAMRasterBand band="31">
    <Metadata>
      <MDI key="STATISTICS_MAXIMUM">37.785203321255</MDI>
      <MDI key="STATISTICS_MEAN">-9999</MDI>
      <MDI key="STATISTICS_MINIMUM">-2.8841533782521</MDI>
      <MDI key="STATISTICS_STDDEV">-9999</MDI>
    </Metadata>
  </PAMRasterBand>
  <PAMRasterBand band="32">
    <Metadata>
      <MDI key="STATISTICS_MAXIMUM">10.499357152327</MDI>
      <MDI key="STATISTICS_MEAN">-9999</MDI>
      <MDI key="STATISTICS_MINIMUM">-2.2900633516037</MDI>
      <MDI key="STATISTICS_STDDEV">-9999</MDI>
    </Metadata>
  </PAMRasterBand>
  <PAMRasterBand band="33">
    <Metadata>
      <MDI key="STATISTICS_MAXIMUM">75.925777679187</MDI>
      <MDI key="STATISTICS_MEAN">-9999</MDI>
      <MDI key="STATISTICS_MINIMUM">-7.1335162022754</MDI>
      <MDI key="STATISTICS_STDDEV">-9999</MDI>
    </Metadata>
  </PAMRasterBand>
  <PAMRasterBand band="34">
    <Metadata>
      <MDI key="STATISTICS_MAXIMUM">164.86251895445</MDI>
      <MDI key="STATISTICS_MEAN">-9999</MDI>
      <MDI key="STATISTICS_MINIMUM">-14.404443829569</MDI>
      <MDI key="STATISTICS_STDDEV">-9999</MDI>
    </Metadata>
  </PAMRasterBand>
  <PAMRasterBand band="35">
    <Metadata>
      <MDI key="STATISTICS_MAXIMUM">300.04332458862</MDI>
      <MDI key="STATISTICS_MEAN">-9999</MDI>
      <MDI key="STATISTICS_MINIMUM">1.6278013863106</MDI>
      <MDI key="STATISTICS_STDDEV">-9999</MDI>
    </Metadata>
  </PAMRasterBand>
  <PAMRasterBand band="36">
    <Metadata>
      <MDI key="STATISTICS_MAXIMUM">343.39320425491</MDI>
      <MDI key="STATISTICS_MEAN">-9999</MDI>
      <MDI key="STATISTICS_MINIMUM">64.007527129613</MDI>
      <MDI key="STATISTICS_STDDEV">-9999</MDI>
    </Metadata>
  </PAMRasterBand>
  <PAMRasterBand band="37">
    <Metadata>
      <MDI key="STATISTICS_MAXIMUM">672.77488190768</MDI>
      <MDI key="STATISTICS_MEAN">-9999</MDI>
      <MDI key="STATISTICS_MINIMUM">21.353522871225</MDI>
      <MDI key="STATISTICS_STDDEV">-9999</MDI>
    </Metadata>
  </PAMRasterBand>
  <PAMRasterBand band="38">
    <Metadata>
      <MDI key="STATISTICS_MAXIMUM">653.82012803189</MDI>
      <MDI key="STATISTICS_MEAN">-9999</MDI>
      <MDI key="STATISTICS_MINIMUM">39.212029707732</MDI>
      <MDI key="STATISTICS_STDDEV">-9999</MDI>
    </Metadata>
  </PAMRasterBand>
  <PAMRasterBand band="39">
    <Metadata>
      <MDI key="STATISTICS_MAXIMUM">697.74002565608</MDI>
      <MDI key="STATISTICS_MEAN">-9999</MDI>
      <MDI key="STATISTICS_MINIMUM">151.7765578375</MDI>
      <MDI key="STATISTICS_STDDEV">-9999</MDI>
    </Metadata>
  </PAMRasterBand>
  <PAMRasterBand band="40">
    <Metadata>
      <MDI key="STATISTICS_MAXIMUM">391.13074214587</MDI>
      <MDI key="STATISTICS_MEAN">-9999</MDI>
      <MDI key="STATISTICS_MINIMUM">11.494554340628</MDI>
      <MDI key="STATISTICS_STDDEV">-9999</MDI>
    </Metadata>
  </PAMRasterBand>
  <PAMRasterBand band="41">
    <Metadata>
      <MDI key="STATISTICS_MAXIMUM">114.08696384207</MDI>
      <MDI key="STATISTICS_MEAN">-9999</MDI>
      <MDI key="STATISTICS_MINIMUM">-4.648335940523</MDI>
      <MDI key="STATISTICS_STDDEV">-9999</MDI>
    </Metadata>
  </PAMRasterBand>
  <PAMRasterBand band="42">
    <Metadata>
      <MDI key="STATISTICS_MAXIMUM">24.522121222515</MDI>
      <MDI key="STATISTICS_MEAN">-9999</MDI>
      <MDI key="STATISTICS_MINIMUM">-1.6794861802163</MDI>
      <MDI key="STATISTICS_STDDEV">-9999</MDI>
    </Metadata>
  </PAMRasterBand>
  <PAMRasterBand band="43">
    <Metadata>
      <MDI key="STATISTICS_MAXIMUM">13.413262428899</MDI>
      <MDI key="STATISTICS_MEAN">-9999</MDI>
      <MDI key="STATISTICS_MINIMUM">-1.9312159722742</MDI>
      <MDI key="STATISTICS_STDDEV">-9999</MDI>
    </Metadata>
  </PAMRasterBand>
  <PAMRasterBand band="44">
    <Metadata>
      <MDI key="STATISTICS_MAXIMUM">17.512368317416</MDI>
      <MDI key="STATISTICS_MEAN">-9999</MDI>
      <MDI key="STATISTICS_MINIMUM">-0.46234570087981</MDI>
      <MDI key="STATISTICS_STDDEV">-9999</MDI>
    </Metadata>
  </PAMRasterBand>
  <PAMRasterBand band="45">
    <Metadata>
      <MDI key="STATISTICS_MAXIMUM">82.571607846843</MDI>
      <MDI key="STATISTICS_MEAN">-9999</MDI>
      <MDI key="STATISTICS_MINIMUM">-13.750713376211</MDI>
      <MDI key="STATISTICS_STDDEV">-9999</MDI>
    </Metadata>
  </PAMRasterBand>
  <PAMRasterBand band="46">
    <Metadata>
      <MDI key="STATISTICS_MAXIMUM">225.18184745685</MDI>
      <MDI key="STATISTICS_MEAN">-9999</MDI>
      <MDI key="STATISTICS_MINIMUM">-22.715229924408</MDI>
      <MDI key="STATISTICS_STDDEV">-9999</MDI>
    </Metadata>
  </PAMRasterBand>
  <PAMRasterBand band="47">
    <Metadata>
      <MDI key="STATISTICS_MAXIMUM">155.13432075618</MDI>
      <MDI key="STATISTICS_MEAN">-9999</MDI>
      <MDI key="STATISTICS_MINIMUM">-5.2531728888705</MDI>
      <MDI key="STATISTICS_STDDEV">-9999</MDI>
    </Metadata>
  </PAMRasterBand>
  <PAMRasterBand band="48">
    <Metadata>
      <MDI key="STATISTICS_MAXIMUM">143.37444090016</MDI>
      <MDI key="STATISTICS_MEAN">-9999</MDI>
      <MDI key="STATISTICS_MINIMUM">-5.3101471674727</MDI>
      <MDI key="STATISTICS_STDDEV">-9999</MDI>
    </Metadata>
  </PAMRasterBand>
  <PAMRasterBand band="49">
    <Metadata>
      <MDI key="STATISTICS_MAXIMUM">213.40012354098</MDI>
      <MDI key="STATISTICS_MEAN">-9999</MDI>
      <MDI key="STATISTICS_MINIMUM">18.721057371026</MDI>
      <MDI key="STATISTICS_STDDEV">-9999</MDI>
    </Metadata>
  </PAMRasterBand>
  <PAMRasterBand band="50">
    <Metadata>
      <MDI key="STATISTICS_MAXIMUM">417.80708651036</MDI>
      <MDI key="STATISTICS_MEAN">-9999</MDI>
      <MDI key="STATISTICS_MINIMUM">170.85980943966</MDI>
      <MDI key="STATISTICS_STDDEV">-9999</MDI>
    </Metadata>
  </PAMRasterBand>
  <PAMRasterBand band="51">
    <Metadata>
      <MDI key="STATISTICS_MAXIMUM">298.09548252343</MDI>
      <MDI key="STATISTICS_MEAN">-9999</MDI>
      <MDI key="STATISTICS_MINIMUM">-5.6379230594043</MDI>
      <MDI key="STATISTICS_STDDEV">-9999</MDI>
    </Metadata>
  </PAMRasterBand>
  <PAMRasterBand band="52">
    <Metadata>
      <MDI key="STATISTICS_MAXIMUM">239.16438773889</MDI>
      <MDI key="STATISTICS_MEAN">-9999</MDI>
      <MDI key="STATISTICS_MINIMUM">-5.1945421279171</MDI>
      <MDI key="STATISTICS_STDDEV">-9999</MDI>
    </Metadata>
  </PAMRasterBand>
  <PAMRasterBand band="53">
    <Metadata>
      <MDI key="STATISTICS_MAXIMUM">174.93470336632</MDI>
      <MDI key="STATISTICS_MEAN">-9999</MDI>
      <MDI key="STATISTICS_MINIMUM">8.2449883902425</MDI>
      <MDI key="STATISTICS_STDDEV">-9999</MDI>
    </Metadata>
  </PAMRasterBand>
  <PAMRasterBand band="54">
    <Metadata>
      <MDI key="STATISTICS_MAXIMUM">169.24380481095</MDI>
      <MDI key="STATISTICS_MEAN">-9999</MDI>
      <MDI key="STATISTICS_MINIMUM">-36.153938724047</MDI>
      <MDI key="STATISTICS_STDDEV">-9999</MDI>
    </Metadata>
  </PAMRasterBand>
  <PAMRasterBand band="55">
    <Metadata>
      <MDI key="STATISTICS_MAXIMUM">55.101569848279</MDI>
      <MDI key="STATISTICS_MEAN">-9999</MDI>
      <MDI key="STATISTICS_MINIMUM">-5.559089948825</MDI>
      <MDI key="STATISTICS_STDDEV">-9999</MDI>
    </Metadata>
  </PAMRasterBand>
  <PAMRasterBand band="56">
    <Metadata>
      <MDI key="STATISTICS_MAXIMUM">31.503294890019</MDI>
      <MDI key="STATISTICS_MEAN">-9999</MDI>
      <MDI key="STATISTICS_MINIMUM">-6.3572198681127</MDI>
      <MDI key="STATISTICS_STDDEV">-9999</MDI>
    </Metadata>
  </PAMRasterBand>
  <PAMRasterBand band="57">
    <Metadata>
      <MDI key="STATISTICS_MAXIMUM">239.51520384898</MDI>
      <MDI key="STATISTICS_MEAN">-9999</MDI>
      <MDI key="STATISTICS_MINIMUM">-43.193180802499</MDI>
      <MDI key="STATISTICS_STDDEV">-9999</MDI>
    </Metadata>
  </PAMRasterBand>
  <PAMRasterBand band="58">
    <Metadata>
      <MDI key="STATISTICS_MAXIMUM">174.31255249236</MDI>
      <MDI key="STATISTICS_MEAN">-9999</MDI>
      <MDI key="STATISTICS_MINIMUM">-30.744053826794</MDI>
      <MDI key="STATISTICS_STDDEV">-9999</MDI>
    </Metadata>
  </PAMRasterBand>
  <PAMRasterBand band="59">
    <Metadata>
      <MDI key="STATISTICS_MAXIMUM">148.28934036056</MDI>
      <MDI key="STATISTICS_MEAN">-9999</MDI>
      <MDI key="STATISTICS_MINIMUM">-19.404556995007</MDI>
      <MDI key="STATISTICS_STDDEV">-9999</MDI>
    </Metadata>
  </PAMRasterBand>
  <PAMRasterBand band="60">
    <Metadata>
      <MDI key="STATISTICS_MAXIMUM">264.86124865087</MDI>
      <MDI key="STATISTICS_MEAN">-9999</MDI>
      <MDI key="STATISTICS_MINIMUM">-12.115552230106</MDI>
      <MDI key="STATISTICS_STDDEV">-9999</MDI>
    </Metadata>
  </PAMRasterBand>
  <PAMRasterBand band="61">
    <Metadata>
      <MDI key="STATISTICS_MAXIMUM">137.42167615801</MDI>
      <MDI key="STATISTICS_MEAN">-9999</MDI>
      <MDI key="STATISTICS_MINIMUM">-2.1025476489564</MDI>
      <MDI key="STATISTICS_STDDEV">-9999</MDI>
    </Metadata>
  </PAMRasterBand>
  <PAMRasterBand band="62">
    <Metadata>
      <MDI key="STATISTICS_MAXIMUM">268.43279945824</MDI>
      <MDI key="STATISTICS_MEAN">-9999</MDI>
      <MDI key="STATISTICS_MINIMUM">74.044180190654</MDI>
      <MDI key="STATISTICS_STDDEV">-9999</MDI>
    </Metadata>
  </PAMRasterBand>
  <PAMRasterBand band="63">
    <Metadata>
      <MDI key="STATISTICS_MAXIMUM">814.42860997358</MDI>
      <MDI key="STATISTICS_MEAN">-9999</MDI>
      <MDI key="STATISTICS_MINIMUM">-50.61713216109</MDI>
      <MDI key="STATISTICS_STDDEV">-9999</MDI>
    </Metadata>
  </PAMRasterBand>
  <PAMRasterBand band="64">
    <Metadata>
      <MDI key="STATISTICS_MAXIMUM">366.36873917141</MDI>
      <MDI key="STATISTICS_MEAN">-9999</MDI>
      <MDI key="STATISTICS_MINIMUM">11.376067887148</MDI>
      <MDI key="STATISTICS_STDDEV">-9999</MDI>
    </Metadata>
  </PAMRasterBand>
  <PAMRasterBand band="65">
    <Metadata>
      <MDI key="STATISTICS_MAXIMUM">318.94751007355</MDI>
      <MDI key="STATISTICS_MEAN">-9999</MDI>
      <MDI key="STATISTICS_MINIMUM">-10.069887811366</MDI>
      <MDI key="STATISTICS_STDDEV">-9999</MDI>
    </Metadata>
  </PAMRasterBand>
  <PAMRasterBand band="66">
    <Metadata>
      <MDI key="STATISTICS_MAXIMUM">95.193207918409</MDI>
      <MDI key="STATISTICS_MEAN">-9999</MDI>
      <MDI key="STATISTICS_MINIMUM">-4.2358786986083</MDI>
      <MDI key="STATISTICS_STDDEV">-9999</MDI>
    </Metadata>
  </PAMRasterBand>
  <PAMRasterBand band="67">
    <Metadata>
      <MDI key="STATISTICS_MAXIMUM">17.078388763216</MDI>
      <MDI key="STATISTICS_MEAN">-9999</MDI>
      <MDI key="STATISTICS_MINIMUM">-1.3389925435806</MDI>
      <MDI key="STATISTICS_STDDEV">-9999</MDI>
    </Metadata>
  </PAMRasterBand>
  <PAMRasterBand band="68">
    <Metadata>
      <MDI key="STATISTICS_MAXIMUM">78.793815512303</MDI>
      <MDI key="STATISTICS_MEAN">-9999</MDI>
      <MDI key="STATISTICS_MINIMUM">-7.0161701913263</MDI>
      <MDI key="STATISTICS_STDDEV">-9999</MDI>
    </Metadata>
  </PAMRasterBand>
  <PAMRasterBand band="69">
    <Metadata>
      <MDI key="STATISTICS_MAXIMUM">139.41517436296</MDI>
      <MDI key="STATISTICS_MEAN">-9999</MDI>
      <MDI key="STATISTICS_MINIMUM">-19.624968331365</MDI>
      <MDI key="STATISTICS_STDDEV">-9999</MDI>
    </Metadata>
  </PAMRasterBand>
  <PAMRasterBand band="70">
    <Metadata>
      <MDI key="STATISTICS_MAXIMUM">78.462066443384</MDI>
      <MDI key="STATISTICS_MEAN">-9999</MDI>
      <MDI key="STATISTICS_MINIMUM">-4.2490627842135</MDI>
      <MDI key="STATISTICS_STDDEV">-9999</MDI>
    </Metadata>
  </PAMRasterBand>
  <PAMRasterBand band="71">
    <Metadata>
      <MDI key="STATISTICS_MAXIMUM">84.128752898987</MDI>
      <MDI key="STATISTICS_MEAN">-9999</MDI>
      <MDI key="STATISTICS_MINIMUM">-1.4373700124499</MDI>
      <MDI key="STATISTICS_STDDEV">-9999</MDI>
    </Metadata>
  </PAMRasterBand>
  <PAMRasterBand band="72">
    <Metadata>
      <MDI key="STATISTICS_MAXIMUM">242.86144982215</MDI>
      <MDI key="STATISTICS_MEAN">-9999</MDI>
      <MDI key="STATISTICS_MINIMUM">11.083503809604</MDI>
      <MDI key="STATISTICS_STDDEV">-9999</MDI>
    </Metadata>
  </PAMRasterBand>
  <PAMRasterBand band="73">
    <Metadata>
      <MDI key="STATISTICS_MAXIMUM">422.2552506028</MDI>
      <MDI key="STATISTICS_MEAN">-9999</MDI>
      <MDI key="STATISTICS_MINIMUM">-17.170381010689</MDI>
      <MDI key="STATISTICS_STDDEV">-9999</MDI>
    </Metadata>
  </PAMRasterBand>
  <PAMRasterBand band="74">
    <Metadata>
      <MDI key="STATISTICS_MAXIMUM">236.73467846171</MDI>
      <MDI key="STATISTICS_MEAN">-9999</MDI>
      <MDI key="STATISTICS_MINIMUM">2.4694002527425</MDI>
      <MDI key="STATISTICS_STDDEV">-9999</MDI>
    </Metadata>
  </PAMRasterBand>
  <PAMRasterBand band="75">
    <Metadata>
      <MDI key="STATISTICS_MAXIMUM">588.74067391804</MDI>
      <MDI key="STATISTICS_MEAN">-9999</MDI>
      <MDI key="STATISTICS_MINIMUM">140.69979529716</MDI>
      <MDI key="STATISTICS_STDDEV">-9999</MDI>
    </Metadata>
  </PAMRasterBand>
  <PAMRasterBand band="76">
    <Metadata>
      <MDI key="STATISTICS_MAXIMUM">208.49862098937</MDI>
      <MDI key="STATISTICS_MEAN">-9999</MDI>
      <MDI key="STATISTICS_MINIMUM">-18.106042304551</MDI>
      <MDI key="STATISTICS_STDDEV">-9999</MDI>
    </Metadata>
  </PAMRasterBand>
  <PAMRasterBand band="77">
    <Metadata>
      <MDI key="STATISTICS_MAXIMUM">209.08012187779</MDI>
      <MDI key="STATISTICS_MEAN">-9999</MDI>
      <MDI key="STATISTICS_MINIMUM">-8.3282406895326</MDI>
      <MDI key="STATISTICS_STDDEV">-9999</MDI>
    </Metadata>
  </PAMRasterBand>
  <PAMRasterBand band="78">
    <Metadata>
      <MDI key="STATISTICS_MAXIMUM">42.818744601094</MDI>
      <MDI key="STATISTICS_MEAN">-9999</MDI>
      <MDI key="STATISTICS_MINIMUM">-8.5306055388758</MDI>
      <MDI key="STATISTICS_STDDEV">-9999</MDI>
    </Metadata>
  </PAMRasterBand>
  <PAMRasterBand band="79">
    <Metadata>
      <MDI key="STATISTICS_MAXIMUM">22.489388276129</MDI>
      <MDI key="STATISTICS_MEAN">-9999</MDI>
      <MDI key="STATISTICS_MINIMUM">-4.7797961001163</MDI>
      <MDI key="STATISTICS_STDDEV">-9999</MDI>
    </Metadata>
  </PAMRasterBand>
  <PAMRasterBand band="80">
    <Metadata>
      <MDI key="STATISTICS_MAXIMUM">4.4806488189661</MDI>
      <MDI key="STATISTICS_MEAN">-9999</MDI>
      <MDI key="STATISTICS_MINIMUM">-0.47963123878704</MDI>
      <MDI key="STATISTICS_STDDEV">-9999</MDI>
    </Metadata>
  </PAMRasterBand>
  <PAMRasterBand band="81">
    <Metadata>
      <MDI key="STATISTICS_MAXIMUM">220.45742693609</MDI>
      <MDI key="STATISTICS_MEAN">-9999</MDI>
      <MDI key="STATISTICS_MINIMUM">-28.706935992631</MDI>
      <MDI key="STATISTICS_STDDEV">-9999</MDI>
    </Metadata>
  </PAMRasterBand>
  <PAMRasterBand band="82">
    <Metadata>
      <MDI key="STATISTICS_MAXIMUM">168.68412383866</MDI>
      <MDI key="STATISTICS_MEAN">-9999</MDI>
      <MDI key="STATISTICS_MINIMUM">-14.817032651034</MDI>
      <MDI key="STATISTICS_STDDEV">-9999</MDI>
    </Metadata>
  </PAMRasterBand>
  <PAMRasterBand band="83">
    <Metadata>
      <MDI key="STATISTICS_MAXIMUM">223.55819611778</MDI>
      <MDI key="STATISTICS_MEAN">-9999</MDI>
      <MDI key="STATISTICS_MINIMUM">-25.857347282298</MDI>
      <MDI key="STATISTICS_STDDEV">-9999</MDI>
    </Metadata>
  </PAMRasterBand>
  <PAMRasterBand band="84">
    <Metadata>
      <MDI key="STATISTICS_MAXIMUM">258.9831167197</MDI>
      <MDI key="STATISTICS_MEAN">-9999</MDI>
      <MDI key="STATISTICS_MINIMUM">-27.983632939079</MDI>
      <MDI key="STATISTICS_STDDEV">-9999</MDI>
    </Metadata>
  </PAMRasterBand>
  <PAMRasterBand band="85">
    <Metadata>
      <MDI key="STATISTICS_MAXIMUM">119.40734513386</MDI>
      <MDI key="STATISTICS_MEAN">-9999</MDI>
      <MDI key="STATISTICS_MINIMUM">-7.1283919269756</MDI>
      <MDI key="STATISTICS_STDDEV">-9999</MDI>
    </Metadata>
  </PAMRasterBand>
  <PAMRasterBand band="86">
    <Metadata>
      <MDI key="STATISTICS_MAXIMUM">304.69300859249</MDI>
      <MDI key="STATISTICS_MEAN">-9999</MDI>
      <MDI key="STATISTICS_MINIMUM">35.682420878704</MDI>
      <MDI key="STATISTICS_STDDEV">-9999</MDI>
    </Metadata>
  </PAMRasterBand>
  <PAMRasterBand band="87">
    <Metadata>
      <MDI key="STATISTICS_MAXIMUM">381.51490333477</MDI>
      <MDI key="STATISTICS_MEAN">-9999</MDI>
      <MDI key="STATISTICS_MINIMUM">80.434018057067</MDI>
      <MDI key="STATISTICS_STDDEV">-9999</MDI>
    </Metadata>
  </PAMRasterBand>
  <PAMRasterBand band="88">
    <Metadata>
      <MDI key="STATISTICS_MAXIMUM">255.60425759907</MDI>
      <MDI key="STATISTICS_MEAN">-9999</MDI>
      <MDI key="STATISTICS_MINIMUM">24.06400154908</MDI>
      <MDI key="STATISTICS_STDDEV">-9999</MDI>
    </Metadata>
  </PAMRasterBand>
  <PAMRasterBand band="89">
    <Metadata>
      <MDI key="STATISTICS_MAXIMUM">80.109300578786</MDI>
      <MDI key="STATISTICS_MEAN">-9999</MDI>
      <MDI key="STATISTICS_MINIMUM">-14.152216409434</MDI>
      <MDI key="STATISTICS_STDDEV">-9999</MDI>
    </Metadata>
  </PAMRasterBand>
  <PAMRasterBand band="90">
    <Metadata>
      <MDI key="STATISTICS_MAXIMUM">68.65494674511</MDI>
      <MDI key="STATISTICS_MEAN">-9999</MDI>
      <MDI key="STATISTICS_MINIMUM">-9.2107717380548</MDI>
      <MDI key="STATISTICS_STDDEV">-9999</MDI>
    </Metadata>
  </PAMRasterBand>
  <PAMRasterBand band="91">
    <Metadata>
      <MDI key="STATISTICS_MAXIMUM">45.42158624762</MDI>
      <MDI key="STATISTICS_MEAN">-9999</MDI>
      <MDI key="STATISTICS_MINIMUM">-5.2657401550721</MDI>
      <MDI key="STATISTICS_STDDEV">-9999</MDI>
    </Metadata>
  </PAMRasterBand>
  <PAMRasterBand band="92">
    <Metadata>
      <MDI key="STATISTICS_MAXIMUM">16.786352799919</MDI>
      <MDI key="STATISTICS_MEAN">-9999</MDI>
      <MDI key="STATISTICS_MINIMUM">-1.4779109703231</MDI>
      <MDI key="STATISTICS_STDDEV">-9999</MDI>
    </Metadata>
  </PAMRasterBand>
  <PAMRasterBand band="93">
    <Metadata>
      <MDI key="STATISTICS_MAXIMUM">73.471899781956</MDI>
      <MDI key="STATISTICS_MEAN">-9999</MDI>
      <MDI key="STATISTICS_MINIMUM">-8.0736416746999</MDI>
      <MDI key="STATISTICS_STDDEV">-9999</MDI>
    </Metadata>
  </PAMRasterBand>
  <PAMRasterBand band="94">
    <Metadata>
      <MDI key="STATISTICS_MAXIMUM">225.54642414209</MDI>
      <MDI key="STATISTICS_MEAN">-9999</MDI>
      <MDI key="STATISTICS_MINIMUM">-7.9720109093401</MDI>
      <MDI key="STATISTICS_STDDEV">-9999</MDI>
    </Metadata>
  </PAMRasterBand>
  <PAMRasterBand band="95">
    <Metadata>
      <MDI key="STATISTICS_MAXIMUM">228.74938979437</MDI>
      <MDI key="STATISTICS_MEAN">-9999</MDI>
      <MDI key="STATISTICS_MINIMUM">4.0791850985697</MDI>
      <MDI key="STATISTICS_STDDEV">-9999</MDI>
    </Metadata>
  </PAMRasterBand>
  <PAMRasterBand band="96">
    <Metadata>
      <MDI key="STATISTICS_MAXIMUM">238.73807870438</MDI>
      <MDI key="STATISTICS_MEAN">-9999</MDI>
      <MDI key="STATISTICS_MINIMUM">-13.826022416832</MDI>
      <MDI key="STATISTICS_STDDEV">-9999</MDI>
    </Metadata>
  </PAMRasterBand>
  <PAMRasterBand band="97">
    <Metadata>
      <MDI key="STATISTICS_MAXIMUM">175.07243721661</MDI>
      <MDI key="STATISTICS_MEAN">-9999</MDI>
      <MDI key="STATISTICS_MINIMUM">-0.26702238424007</MDI>
      <MDI key="STATISTICS_STDDEV">-9999</MDI>
    </Metadata>
  </PAMRasterBand>
  <PAMRasterBand band="98">
    <Metadata>
      <MDI key="STATISTICS_MAXIMUM">250.69995990942</MDI>
      <MDI key="STATISTICS_MEAN">-9999</MDI>
      <MDI key="STATISTICS_MINIMUM">16.196368933793</MDI>
      <MDI key="STATISTICS_STDDEV">-9999</MDI>
    </Metadata>
  </PAMRasterBand>
  <PAMRasterBand band="99">
    <Metadata>
      <MDI key="STATISTICS_MAXIMUM">226.26584423071</MDI>
      <MDI key="STATISTICS_MEAN">-9999</MDI>
      <MDI key="STATISTICS_MINIMUM">-8.2304406164173</MDI>
      <MDI key="STATISTICS_STDDEV">-9999</MDI>
    </Metadata>
  </PAMRasterBand>
  <PAMRasterBand band="100">
    <Metadata>
      <MDI key="STATISTICS_MAXIMUM">151.96921267287</MDI>
      <MDI key="STATISTICS_MEAN">-9999</MDI>
      <MDI key="STATISTICS_MINIMUM">1.1102433517676</MDI>
      <MDI key="STATISTICS_STDDEV">-9999</MDI>
    </Metadata>
  </PAMRasterBand>
  <PAMRasterBand band="101">
    <Metadata>
      <MDI key="STATISTICS_MAXIMUM">83.824535048374</MDI>
      <MDI key="STATISTICS_MEAN">-9999</MDI>
      <MDI key="STATISTICS_MINIMUM">-9.1016396662544</MDI>
      <MDI key="STATISTICS_STDDEV">-9999</MDI>
    </Metadata>
  </PAMRasterBand>
  <PAMRasterBand band="102">
    <Metadata>
      <MDI key="STATISTICS_MAXIMUM">103.3404192466</MDI>
      <MDI key="STATISTICS_MEAN">-9999</MDI>
      <MDI key="STATISTICS_MINIMUM">-18.730294936286</MDI>
      <MDI key="STATISTICS_STDDEV">-9999</MDI>
    </Metadata>
  </PAMRasterBand>
  <PAMRasterBand band="103">
    <Metadata>
      <MDI key="STATISTICS_MAXIMUM">28.579699993288</MDI>
      <MDI key="STATISTICS_MEAN">-9999</MDI>
      <MDI key="STATISTICS_MINIMUM">-4.757438403425</MDI>
      <MDI key="STATISTICS_STDDEV">-9999</MDI>
    </Metadata>
  </PAMRasterBand>
  <PAMRasterBand band="104">
    <Metadata>
      <MDI key="STATISTICS_MAXIMUM">47.162429226516</MDI>
      <MDI key="STATISTICS_MEAN">-9999</MDI>
      <MDI key="STATISTICS_MINIMUM">-2.6442790593016</MDI>
      <MDI key="STATISTICS_STDDEV">-9999</MDI>
    </Metadata>
  </PAMRasterBand>
  <PAMRasterBand band="105">
    <Metadata>
      <MDI key="STATISTICS_MAXIMUM">137.11100768318</MDI>
      <MDI key="STATISTICS_MEAN">-9999</MDI>
      <MDI key="STATISTICS_MINIMUM">-9.9121999404359</MDI>
      <MDI key="STATISTICS_STDDEV">-9999</MDI>
    </Metadata>
  </PAMRasterBand>
  <PAMRasterBand band="106">
    <Metadata>
      <MDI key="STATISTICS_MAXIMUM">113.49259598497</MDI>
      <MDI key="STATISTICS_MEAN">-9999</MDI>
      <MDI key="STATISTICS_MINIMUM">-9.9613935457041</MDI>
      <MDI key="STATISTICS_STDDEV">-9999</MDI>
    </Metadata>
  </PAMRasterBand>
  <PAMRasterBand band="107">
    <Metadata>
      <MDI key="STATISTICS_MAXIMUM">165.25894960501</MDI>
      <MDI key="STATISTICS_MEAN">-9999</MDI>
      <MDI key="STATISTICS_MINIMUM">-8.168094095631</MDI>
      <MDI key="STATISTICS_STDDEV">-9999</MDI>
    </Metadata>
  </PAMRasterBand>
  <PAMRasterBand band="108">
    <Metadata>
      <MDI key="STATISTICS_MAXIMUM">137.10920422333</MDI>
      <MDI key="STATISTICS_MEAN">-9999</MDI>
      <MDI key="STATISTICS_MINIMUM">7.3068820452797</MDI>
      <MDI key="STATISTICS_STDDEV">-9999</MDI>
    </Metadata>
  </PAMRasterBand>
  <PAMRasterBand band="109">
    <Metadata>
      <MDI key="STATISTICS_MAXIMUM">131.6986748101</MDI>
      <MDI key="STATISTICS_MEAN">-9999</MDI>
      <MDI key="STATISTICS_MINIMUM">-14.93913720173</MDI>
      <MDI key="STATISTICS_STDDEV">-9999</MDI>
    </Metadata>
  </PAMRasterBand>
  <PAMRasterBand band="110">
    <Metadata>
      <MDI key="STATISTICS_MAXIMUM">267.45292138069</MDI>
      <MDI key="STATISTICS_MEAN">-9999</MDI>
      <MDI key="STATISTICS_MINIMUM">5.5165922009708</MDI>
      <MDI key="STATISTICS_STDDEV">-9999</MDI>
    </Metadata>
  </PAMRasterBand>
  <PAMRasterBand band="111">
    <Metadata>
      <MDI key="STATISTICS_MAXIMUM">197.23311912794</MDI>
      <MDI key="STATISTICS_MEAN">-9999</MDI>
      <MDI key="STATISTICS_MINIMUM">-3.3102474525125</MDI>
      <MDI key="STATISTICS_STDDEV">-9999</MDI>
    </Metadata>
  </PAMRasterBand>
  <PAMRasterBand band="112">
    <Metadata>
      <MDI key="STATISTICS_MAXIMUM">153.69984025087</MDI>
      <MDI key="STATISTICS_MEAN">-9999</MDI>
      <MDI key="STATISTICS_MINIMUM">-10.895027112485</MDI>
      <MDI key="STATISTICS_STDDEV">-9999</MDI>
    </Metadata>
  </PAMRasterBand>
  <PAMRasterBand band="113">
    <Metadata>
      <MDI key="STATISTICS_MAXIMUM">110.80657525469</MDI>
      <MDI key="STATISTICS_MEAN">-9999</MDI>
      <MDI key="STATISTICS_MINIMUM">-23.4998915615</MDI>
      <MDI key="STATISTICS_STDDEV">-9999</MDI>
    </Metadata>
  </PAMRasterBand>
  <PAMRasterBand band="114">
    <Metadata>
      <MDI key="STATISTICS_MAXIMUM">16.02316597112</MDI>
      <MDI key="STATISTICS_MEAN">-9999</MDI>
      <MDI key="STATISTICS_MINIMUM">-2.734601712339</MDI>
      <MDI key="STATISTICS_STDDEV">-9999</MDI>
    </Metadata>
  </PAMRasterBand>
  <PAMRasterBand band="115">
    <Metadata>
      <MDI key="STATISTICS_MAXIMUM">86.801117173682</MDI>
      <MDI key="STATISTICS_MEAN">-9999</MDI>
      <MDI key="STATISTICS_MINIMUM">-26.484160839714</MDI>
      <MDI key="STATISTICS_STDDEV">-9999</MDI>
    </Metadata>
  </PAMRasterBand>
  <PAMRasterBand band="116">
    <Metadata>
      <MDI key="STATISTICS_MAXIMUM">19.894156387185</MDI>
      <MDI key="STATISTICS_MEAN">-9999</MDI>
      <MDI key="STATISTICS_MINIMUM">-4.7957496868679</MDI>
      <MDI key="STATISTICS_STDDEV">-9999</MDI>
    </Metadata>
  </PAMRasterBand>
  <PAMRasterBand band="117">
    <Metadata>
      <MDI key="STATISTICS_MAXIMUM">129.09101777752</MDI>
      <MDI key="STATISTICS_MEAN">-9999</MDI>
      <MDI key="STATISTICS_MINIMUM">-30.668926673767</MDI>
      <MDI key="STATISTICS_STDDEV">-9999</MDI>
    </Metadata>
  </PAMRasterBand>
  <PAMRasterBand band="118">
    <Metadata>
      <MDI key="STATISTICS_MAXIMUM">204.15058632058</MDI>
      <MDI key="STATISTICS_MEAN">-9999</MDI>
      <MDI key="STATISTICS_MINIMUM">-18.299922037367</MDI>
      <MDI key="STATISTICS_STDDEV">-9999</MDI>
    </Metadata>
  </PAMRasterBand>
  <PAMRasterBand band="119">
    <Metadata>
      <MDI key="STATISTICS_MAXIMUM">234.49169274043</MDI>
      <MDI key="STATISTICS_MEAN">-9999</MDI>
      <MDI key="STATISTICS_MINIMUM">-33.171512054351</MDI>
      <MDI key="STATISTICS_STDDEV">-9999</MDI>
    </Metadata>
  </PAMRasterBand>
  <PAMRasterBand band="120">
    <Metadata>
      <MDI key="STATISTICS_MAXIMUM">240.74260006965</MDI>
      <MDI key="STATISTICS_MEAN">-9999</MDI>
      <MDI key="STATISTICS_MINIMUM">-24.04815631614</MDI>
      <MDI key="STATISTICS_STDDEV">-9999</MDI>
    </Metadata>
  </PAMRasterBand>
  <PAMRasterBand band="121">
    <Metadata>
      <MDI key="STATISTICS_MAXIMUM">170.9355863464</MDI>
      <MDI key="STATISTICS_MEAN">-9999</MDI>
      <MDI key="STATISTICS_MINIMUM">-8.5586404355467</MDI>
      <MDI key="STATISTICS_STDDEV">-9999</MDI>
    </Metadata>
  </PAMRasterBand>
  <PAMRasterBand band="122">
    <Metadata>
      <MDI key="STATISTICS_MAXIMUM">249.71834743298</MDI>
      <MDI key="STATISTICS_MEAN">-9999</MDI>
      <MDI key="STATISTICS_MINIMUM">-4.2636617773962</MDI>
      <MDI key="STATISTICS_STDDEV">-9999</MDI>
    </Metadata>
  </PAMRasterBand>
  <PAMRasterBand band="123">
    <Metadata>
      <MDI key="STATISTICS_MAXIMUM">423.22182502572</MDI>
      <MDI key="STATISTICS_MEAN">-9999</MDI>
      <MDI key="STATISTICS_MINIMUM">51.312235417086</MDI>
      <MDI key="STATISTICS_STDDEV">-9999</MDI>
    </Metadata>
  </PAMRasterBand>
  <PAMRasterBand band="124">
    <Metadata>
      <MDI key="STATISTICS_MAXIMUM">124.13477363351</MDI>
      <MDI key="STATISTICS_MEAN">-9999</MDI>
      <MDI key="STATISTICS_MINIMUM">-6.7432804212882</MDI>
      <MDI key="STATISTICS_STDDEV">-9999</MDI>
    </Metadata>
  </PAMRasterBand>
  <PAMRasterBand band="125">
    <Metadata>
      <MDI key="STATISTICS_MAXIMUM">89.644733545123</MDI>
      <MDI key="STATISTICS_MEAN">-9999</MDI>
      <MDI key="STATISTICS_MINIMUM">-10.753348732636</MDI>
      <MDI key="STATISTICS_STDDEV">-9999</MDI>
    </Metadata>
  </PAMRasterBand>
  <PAMRasterBand band="126">
    <Metadata>
      <MDI key="STATISTICS_MAXIMUM">52.26925660084</MDI>
      <MDI key="STATISTICS_MEAN">-9999</MDI>
      <MDI key="STATISTICS_MINIMUM">-2.7254158447628</MDI>
      <MDI key="STATISTICS_STDDEV">-9999</MDI>
    </Metadata>
  </PAMRasterBand>
  <PAMRasterBand band="127">
    <Metadata>
      <MDI key="STATISTICS_MAXIMUM">7.596579937113</MDI>
      <MDI key="STATISTICS_MEAN">-9999</MDI>
      <MDI key="STATISTICS_MINIMUM">-1.347950088979</MDI>
      <MDI key="STATISTICS_STDDEV">-9999</MDI>
    </Metadata>
  </PAMRasterBand>
  <PAMRasterBand band="128">
    <Metadata>
      <MDI key="STATISTICS_MAXIMUM">26.128598920768</MDI>
      <MDI key="STATISTICS_MEAN">-9999</MDI>
      <MDI key="STATISTICS_MINIMUM">-3.9896410100936</MDI>
      <MDI key="STATISTICS_STDDEV">-9999</MDI>
    </Metadata>
  </PAMRasterBand>
  <PAMRasterBand band="129">
    <Metadata>
      <MDI key="STATISTICS_MAXIMUM">60.657948844277</MDI>
      <MDI key="STATISTICS_MEAN">-9999</MDI>
      <MDI key="STATISTICS_MINIMUM">-7.1342021018767</MDI>
      <MDI key="STATISTICS_STDDEV">-9999</MDI>
    </Metadata>
  </PAMRasterBand>
  <PAMRasterBand band="130">
    <Metadata>
      <MDI key="STATISTICS_MAXIMUM">300.32097713224</MDI>
      <MDI key="STATISTICS_MEAN">-9999</MDI>
      <MDI key="STATISTICS_MINIMUM">-33.842789510076</MDI>
      <MDI key="STATISTICS_STDDEV">-9999</MDI>
    </Metadata>
  </PAMRasterBand>
  <PAMRasterBand band="131">
    <Metadata>
      <MDI key="STATISTICS_MAXIMUM">113.46315100301</MDI>
      <MDI key="STATISTICS_MEAN">-9999</MDI>
      <MDI key="STATISTICS_MINIMUM">-7.9529849979204</MDI>
      <MDI key="STATISTICS_STDDEV">-9999</MDI>
    </Metadata>
  </PAMRasterBand>
  <PAMRasterBand band="132">
    <Metadata>
      <MDI key="STATISTICS_MAXIMUM">184.04480942083</MDI>
      <MDI key="STATISTICS_MEAN">-9999</MDI>
      <MDI key="STATISTICS_MINIMUM">-17.031620050032</MDI>
      <MDI key="STATISTICS_STDDEV">-9999</MDI>
    </Metadata>
  </PAMRasterBand>
  <PAMRasterBand band="133">
    <Metadata>
      <MDI key="STATISTICS_MAXIMUM">199.13479806038</MDI>
      <MDI key="STATISTICS_MEAN">-9999</MDI>
      <MDI key="STATISTICS_MINIMUM">31.912819641255</MDI>
      <MDI key="STATISTICS_STDDEV">-9999</MDI>
    </Metadata>
  </PAMRasterBand>
  <PAMRasterBand band="134">
    <Metadata>
      <MDI key="STATISTICS_MAXIMUM">315.0651139748</MDI>
      <MDI key="STATISTICS_MEAN">-9999</MDI>
      <MDI key="STATISTICS_MINIMUM">54.766188702743</MDI>
      <MDI key="STATISTICS_STDDEV">-9999</MDI>
    </Metadata>
  </PAMRasterBand>
  <PAMRasterBand band="135">
    <Metadata>
      <MDI key="STATISTICS_MAXIMUM">624.1693228304</MDI>
      <MDI key="STATISTICS_MEAN">-9999</MDI>
      <MDI key="STATISTICS_MINIMUM">132.47685361887</MDI>
      <MDI key="STATISTICS_STDDEV">-9999</MDI>
    </Metadata>
  </PAMRasterBand>
  <PAMRasterBand band="136">
    <Metadata>
      <MDI key="STATISTICS_MAXIMUM">170.17627374534</MDI>
      <MDI key="STATISTICS_MEAN">-9999</MDI>
      <MDI key="STATISTICS_MINIMUM">15.554316541801</MDI>
      <MDI key="STATISTICS_STDDEV">-9999</MDI>
    </Metadata>
  </PAMRasterBand>
  <PAMRasterBand band="137">
    <Metadata>
      <MDI key="STATISTICS_MAXIMUM">61.774616066257</MDI>
      <MDI key="STATISTICS_MEAN">-9999</MDI>
      <MDI key="STATISTICS_MINIMUM">-6.539476742261</MDI>
      <MDI key="STATISTICS_STDDEV">-9999</MDI>
    </Metadata>
  </PAMRasterBand>
  <PAMRasterBand band="138">
    <Metadata>
      <MDI key="STATISTICS_MAXIMUM">83.884856759757</MDI>
      <MDI key="STATISTICS_MEAN">-9999</MDI>
      <MDI key="STATISTICS_MINIMUM">-2.4444739255041</MDI>
      <MDI key="STATISTICS_STDDEV">-9999</MDI>
    </Metadata>
  </PAMRasterBand>
  <PAMRasterBand band="139">
    <Metadata>
      <MDI key="STATISTICS_MAXIMUM">39.268871892939</MDI>
      <MDI key="STATISTICS_MEAN">-9999</MDI>
      <MDI key="STATISTICS_MINIMUM">-8.7754517334302</MDI>
      <MDI key="STATISTICS_STDDEV">-9999</MDI>
    </Metadata>
  </PAMRasterBand>
  <PAMRasterBand band="140">
    <Metadata>
      <MDI key="STATISTICS_MAXIMUM">31.667387495794</MDI>
      <MDI key="STATISTICS_MEAN">-9999</MDI>
      <MDI key="STATISTICS_MINIMUM">-2.5616566162337</MDI>
      <MDI key="STATISTICS_STDDEV">-9999</MDI>
    </Metadata>
  </PAMRasterBand>
  <PAMRasterBand band="141">
    <Metadata>
      <MDI key="STATISTICS_MAXIMUM">132.7842214519</MDI>
      <MDI key="STATISTICS_MEAN">-9999</MDI>
      <MDI key="STATISTICS_MINIMUM">-8.6389989265147</MDI>
      <MDI key="STATISTICS_STDDEV">-9999</MDI>
    </Metadata>
  </PAMRasterBand>
  <PAMRasterBand band="142">
    <Metadata>
      <MDI key="STATISTICS_MAXIMUM">109.06443113964</MDI>
      <MDI key="STATISTICS_MEAN">-9999</MDI>
      <MDI key="STATISTICS_MINIMUM">-16.205781788795</MDI>
      <MDI key="STATISTICS_STDDEV">-9999</MDI>
    </Metadata>
  </PAMRasterBand>
  <PAMRasterBand band="143">
    <Metadata>
      <MDI key="STATISTICS_MAXIMUM">202.74195506696</MDI>
      <MDI key="STATISTICS_MEAN">-9999</MDI>
      <MDI key="STATISTICS_MINIMUM">-13.734862619211</MDI>
      <MDI key="STATISTICS_STDDEV">-9999</MDI>
    </Metadata>
  </PAMRasterBand>
  <PAMRasterBand band="144">
    <Metadata>
      <MDI key="STATISTICS_MAXIMUM">294.14245660776</MDI>
      <MDI key="STATISTICS_MEAN">-9999</MDI>
      <MDI key="STATISTICS_MINIMUM">-35.596389122558</MDI>
      <MDI key="STATISTICS_STDDEV">-9999</MDI>
    </Metadata>
  </PAMRasterBand>
  <PAMRasterBand band="145">
    <Metadata>
      <MDI key="STATISTICS_MAXIMUM">288.13383516748</MDI>
      <MDI key="STATISTICS_MEAN">-9999</MDI>
      <MDI key="STATISTICS_MINIMUM">-14.516942804331</MDI>
      <MDI key="STATISTICS_STDDEV">-9999</MDI>
    </Metadata>
  </PAMRasterBand>
  <PAMRasterBand band="146">
    <Metadata>
      <MDI key="STATISTICS_MAXIMUM">123.99167840255</MDI>
      <MDI key="STATISTICS_MEAN">-9999</MDI>
      <MDI key="STATISTICS_MINIMUM">-6.2701905724806</MDI>
      <MDI key="STATISTICS_STDDEV">-9999</MDI>
    </Metadata>
  </PAMRasterBand>
  <PAMRasterBand band="147">
    <Metadata>
      <MDI key="STATISTICS_MAXIMUM">432.87311988935</MDI>
      <MDI key="STATISTICS_MEAN">-9999</MDI>
      <MDI key="STATISTICS_MINIMUM">63.695479716701</MDI>
      <MDI key="STATISTICS_STDDEV">-9999</MDI>
    </Metadata>
  </PAMRasterBand>
  <PAMRasterBand band="148">
    <Metadata>
      <MDI key="STATISTICS_MAXIMUM">244.5099825379</MDI>
      <MDI key="STATISTICS_MEAN">-9999</MDI>
      <MDI key="STATISTICS_MINIMUM">4.3389157464913</MDI>
      <MDI key="STATISTICS_STDDEV">-9999</MDI>
    </Metadata>
  </PAMRasterBand>
  <PAMRasterBand band="149">
    <Metadata>
      <MDI key="STATISTICS_MAXIMUM">107.4009054644</MDI>
      <MDI key="STATISTICS_MEAN">-9999</MDI>
      <MDI key="STATISTICS_MINIMUM">5.2939499078017</MDI>
      <MDI key="STATISTICS_STDDEV">-9999</MDI>
    </Metadata>
  </PAMRasterBand>
  <PAMRasterBand band="150">
    <Metadata>
      <MDI key="STATISTICS_MAXIMUM">14.682616178935</MDI>
      <MDI key="STATISTICS_MEAN">-9999</MDI>
      <MDI key="STATISTICS_MINIMUM">-2.7148164346042</MDI>
      <MDI key="STATISTICS_STDDEV">-9999</MDI>
    </Metadata>
  </PAMRasterBand>
  <PAMRasterBand band="151">
    <Metadata>
      <MDI key="STATISTICS_MAXIMUM">57.648224053586</MDI>
      <MDI key="STATISTICS_MEAN">-9999</MDI>
      <MDI key="STATISTICS_MINIMUM">-3.8031957407988</MDI>
      <MDI key="STATISTICS_STDDEV">-9999</MDI>
    </Metadata>
  </PAMRasterBand>
  <PAMRasterBand band="152">
    <Metadata>
      <MDI key="STATISTICS_MAXIMUM">42.530388951935</MDI>
      <MDI key="STATISTICS_MEAN">-9999</MDI>
      <MDI key="STATISTICS_MINIMUM">-7.2210827883931</MDI>
      <MDI key="STATISTICS_STDDEV">-9999</MDI>
    </Metadata>
  </PAMRasterBand>
  <PAMRasterBand band="153">
    <Metadata>
      <MDI key="STATISTICS_MAXIMUM">59.562416199018</MDI>
      <MDI key="STATISTICS_MEAN">-9999</MDI>
      <MDI key="STATISTICS_MINIMUM">-9.185495420562</MDI>
      <MDI key="STATISTICS_STDDEV">-9999</MDI>
    </Metadata>
  </PAMRasterBand>
  <PAMRasterBand band="154">
    <Metadata>
      <MDI key="STATISTICS_MAXIMUM">253.22760185977</MDI>
      <MDI key="STATISTICS_MEAN">-9999</MDI>
      <MDI key="STATISTICS_MINIMUM">-27.043562414197</MDI>
      <MDI key="STATISTICS_STDDEV">-9999</MDI>
    </Metadata>
  </PAMRasterBand>
  <PAMRasterBand band="155">
    <Metadata>
      <MDI key="STATISTICS_MAXIMUM">240.30115929542</MDI>
      <MDI key="STATISTICS_MEAN">-9999</MDI>
      <MDI key="STATISTICS_MINIMUM">-9.6088744730455</MDI>
      <MDI key="STATISTICS_STDDEV">-9999</MDI>
    </Metadata>
  </PAMRasterBand>
  <PAMRasterBand band="156">
    <Metadata>
      <MDI key="STATISTICS_MAXIMUM">165.61300396556</MDI>
      <MDI key="STATISTICS_MEAN">-9999</MDI>
      <MDI key="STATISTICS_MINIMUM">-19.17654461617</MDI>
      <MDI key="STATISTICS_STDDEV">-9999</MDI>
    </Metadata>
  </PAMRasterBand>
  <PAMRasterBand band="157">
    <Metadata>
      <MDI key="STATISTICS_MAXIMUM">292.68271568612</MDI>
      <MDI key="STATISTICS_MEAN">-9999</MDI>
      <MDI key="STATISTICS_MINIMUM">36.053275330706</MDI>
      <MDI key="STATISTICS_STDDEV">-9999</MDI>
    </Metadata>
  </PAMRasterBand>
  <PAMRasterBand band="158">
    <Metadata>
      <MDI key="STATISTICS_MAXIMUM">469.30101104077</MDI>
      <MDI key="STATISTICS_MEAN">-9999</MDI>
      <MDI key="STATISTICS_MINIMUM">123.54215156926</MDI>
      <MDI key="STATISTICS_STDDEV">-9999</MDI>
    </Metadata>
  </PAMRasterBand>
  <PAMRasterBand band="159">
    <Metadata>
      <MDI key="STATISTICS_MAXIMUM">319.95013707262</MDI>
      <MDI key="STATISTICS_MEAN">-9999</MDI>
      <MDI key="STATISTICS_MINIMUM">88.329197218254</MDI>
      <MDI key="STATISTICS_STDDEV">-9999</MDI>
    </Metadata>
  </PAMRasterBand>
  <PAMRasterBand band="160">
    <Metadata>
      <MDI key="STATISTICS_MAXIMUM">227.27741119682</MDI>
      <MDI key="STATISTICS_MEAN">-9999</MDI>
      <MDI key="STATISTICS_MINIMUM">40.196627639026</MDI>
      <MDI key="STATISTICS_STDDEV">-9999</MDI>
    </Metadata>
  </PAMRasterBand>
  <PAMRasterBand band="161">
    <Metadata>
      <MDI key="STATISTICS_MAXIMUM">149.72542313321</MDI>
      <MDI key="STATISTICS_MEAN">-9999</MDI>
      <MDI key="STATISTICS_MINIMUM">-17.880827788221</MDI>
      <MDI key="STATISTICS_STDDEV">-9999</MDI>
    </Metadata>
  </PAMRasterBand>
  <PAMRasterBand band="162">
    <Metadata>
      <MDI key="STATISTICS_MAXIMUM">72.052156193344</MDI>
      <MDI key="STATISTICS_MEAN">-9999</MDI>
      <MDI key="STATISTICS_MINIMUM">-6.01133343064</MDI>
      <MDI key="STATISTICS_STDDEV">-9999</MDI>
    </Metadata>
  </PAMRasterBand>
  <PAMRasterBand band="163">
    <Metadata>
      <MDI key="STATISTICS_MAXIMUM">46.706574912057</MDI>
      <MDI key="STATISTICS_MEAN">-9999</MDI>
      <MDI key="STATISTICS_MINIMUM">-2.6918882010626</MDI>
      <MDI key="STATISTICS_STDDEV">-9999</MDI>
    </Metadata>
  </PAMRasterBand>
  <PAMRasterBand band="164">
    <Metadata>
      <MDI key="STATISTICS_MAXIMUM">115.49752528838</MDI>
      <MDI key="STATISTICS_MEAN">-9999</MDI>
      <MDI key="STATISTICS_MINIMUM">0.57909373592736</MDI>
      <MDI key="STATISTICS_STDDEV">-9999</MDI>
    </Metadata>
  </PAMRasterBand>
  <PAMRasterBand band="165">
    <Metadata>
      <MDI key="STATISTICS_MAXIMUM">284.97726667506</MDI>
      <MDI key="STATISTICS_MEAN">-9999</MDI>
      <MDI key="STATISTICS_MINIMUM">-16.610155171417</MDI>
      <MDI key="STATISTICS_STDDEV">-9999</MDI>
    </Metadata>
  </PAMRasterBand>
  <PAMRasterBand band="166">
    <Metadata>
      <MDI key="STATISTICS_MAXIMUM">270.36491441353</MDI>
      <MDI key="STATISTICS_MEAN">-9999</MDI>
      <MDI key="STATISTICS_MINIMUM">-48.460836594007</MDI>
      <MDI key="STATISTICS_STDDEV">-9999</MDI>
    </Metadata>
  </PAMRasterBand>
  <PAMRasterBand band="167">
    <Metadata>
      <MDI key="STATISTICS_MAXIMUM">133.30667779582</MDI>
      <MDI key="STATISTICS_MEAN">-9999</MDI>
      <MDI key="STATISTICS_MINIMUM">12.851179483358</MDI>
      <MDI key="STATISTICS_STDDEV">-9999</MDI>
    </Metadata>
  </PAMRasterBand>
  <PAMRasterBand band="168">
    <Metadata>
      <MDI key="STATISTICS_MAXIMUM">66.408225519488</MDI>
      <MDI key="STATISTICS_MEAN">-9999</MDI>
      <MDI key="STATISTICS_MINIMUM">-10.387093902898</MDI>
      <MDI key="STATISTICS_STDDEV">-9999</MDI>
    </Metadata>
  </PAMRasterBand>
  <PAMRasterBand band="169">
    <Metadata>
      <MDI key="STATISTICS_MAXIMUM">425.83523496982</MDI>
      <MDI key="STATISTICS_MEAN">-9999</MDI>
      <MDI key="STATISTICS_MINIMUM">55.720934915473</MDI>
      <MDI key="STATISTICS_STDDEV">-9999</MDI>
    </Metadata>
  </PAMRasterBand>
  <PAMRasterBand band="170">
    <Metadata>
      <MDI key="STATISTICS_MAXIMUM">319.90918592322</MDI>
      <MDI key="STATISTICS_MEAN">-9999</MDI>
      <MDI key="STATISTICS_MINIMUM">55.458422016463</MDI>
      <MDI key="STATISTICS_STDDEV">-9999</MDI>
    </Metadata>
  </PAMRasterBand>
  <PAMRasterBand band="171">
    <Metadata>
      <MDI key="STATISTICS_MAXIMUM">492.91080487074</MDI>
      <MDI key="STATISTICS_MEAN">-9999</MDI>
      <MDI key="STATISTICS_MINIMUM">63.587123726435</MDI>
      <MDI key="STATISTICS_STDDEV">-9999</MDI>
    </Metadata>
  </PAMRasterBand>
  <PAMRasterBand band="172">
    <Metadata>
      <MDI key="STATISTICS_MAXIMUM">193.30661566331</MDI>
      <MDI key="STATISTICS_MEAN">-9999</MDI>
      <MDI key="STATISTICS_MINIMUM">-18.060878934846</MDI>
      <MDI key="STATISTICS_STDDEV">-9999</MDI>
    </Metadata>
  </PAMRasterBand>
  <PAMRasterBand band="173">
    <Metadata>
      <MDI key="STATISTICS_MAXIMUM">167.14528546778</MDI>
      <MDI key="STATISTICS_MEAN">-9999</MDI>
      <MDI key="STATISTICS_MINIMUM">-22.308299612745</MDI>
      <MDI key="STATISTICS_STDDEV">-9999</MDI>
    </Metadata>
  </PAMRasterBand>
  <PAMRasterBand band="174">
    <Metadata>
      <MDI key="STATISTICS_MAXIMUM">67.324574870923</MDI>
      <MDI key="STATISTICS_MEAN">-9999</MDI>
      <MDI key="STATISTICS_MINIMUM">-8.9242612409537</MDI>
      <MDI key="STATISTICS_STDDEV">-9999</MDI>
    </Metadata>
  </PAMRasterBand>
  <PAMRasterBand band="175">
    <Metadata>
      <MDI key="STATISTICS_MAXIMUM">47.946525924008</MDI>
      <MDI key="STATISTICS_MEAN">-9999</MDI>
      <MDI key="STATISTICS_MINIMUM">-6.2982582428207</MDI>
      <MDI key="STATISTICS_STDDEV">-9999</MDI>
    </Metadata>
  </PAMRasterBand>
  <PAMRasterBand band="176">
    <Metadata>
      <MDI key="STATISTICS_MAXIMUM">33.31152178234</MDI>
      <MDI key="STATISTICS_MEAN">-9999</MDI>
      <MDI key="STATISTICS_MINIMUM">-4.1233751189012</MDI>
      <MDI key="STATISTICS_STDDEV">-9999</MDI>
    </Metadata>
  </PAMRasterBand>
  <PAMRasterBand band="177">
    <Metadata>
      <MDI key="STATISTICS_MAXIMUM">65.08288527611</MDI>
      <MDI key="STATISTICS_MEAN">-9999</MDI>
      <MDI key="STATISTICS_MINIMUM">-7.4490328588953</MDI>
      <MDI key="STATISTICS_STDDEV">-9999</MDI>
    </Metadata>
  </PAMRasterBand>
  <PAMRasterBand band="178">
    <Metadata>
      <MDI key="STATISTICS_MAXIMUM">202.23894159184</MDI>
      <MDI key="STATISTICS_MEAN">-9999</MDI>
      <MDI key="STATISTICS_MINIMUM">-29.252847934863</MDI>
      <MDI key="STATISTICS_STDDEV">-9999</MDI>
    </Metadata>
  </PAMRasterBand>
  <PAMRasterBand band="179">
    <Metadata>
      <MDI key="STATISTICS_MAXIMUM">259.92190019663</MDI>
      <MDI key="STATISTICS_MEAN">-9999</MDI>
      <MDI key="STATISTICS_MINIMUM">-44.020554668799</MDI>
      <MDI key="STATISTICS_STDDEV">-9999</MDI>
    </Metadata>
  </PAMRasterBand>
  <PAMRasterBand band="180">
    <Metadata>
      <MDI key="STATISTICS_MAXIMUM">232.88131296994</MDI>
      <MDI key="STATISTICS_MEAN">-9999</MDI>
      <MDI key="STATISTICS_MINIMUM">-19.646553854091</MDI>
      <MDI key="STATISTICS_STDDEV">-9999</MDI>
    </Metadata>
  </PAMRasterBand>
  <PAMRasterBand band="181">
    <Metadata>
      <MDI key="STATISTICS_MAXIMUM">121.68905819383</MDI>
      <MDI key="STATISTICS_MEAN">-9999</MDI>
      <MDI key="STATISTICS_MINIMUM">2.4558076296863</MDI>
      <MDI key="STATISTICS_STDDEV">-9999</MDI>
    </Metadata>
  </PAMRasterBand>
  <PAMRasterBand band="182">
    <Metadata>
      <MDI key="STATISTICS_MAXIMUM">254.27269057813</MDI>
      <MDI key="STATISTICS_MEAN">-9999</MDI>
      <MDI key="STATISTICS_MINIMUM">92.893533824098</MDI>
      <MDI key="STATISTICS_STDDEV">-9999</MDI>
    </Metadata>
  </PAMRasterBand>
  <PAMRasterBand band="183">
    <Metadata>
      <MDI key="STATISTICS_MAXIMUM">369.12158037147</MDI>
      <MDI key="STATISTICS_MEAN">-9999</MDI>
      <MDI key="STATISTICS_MINIMUM">1.9461925892556</MDI>
      <MDI key="STATISTICS_STDDEV">-9999</MDI>
    </Metadata>
  </PAMRasterBand>
  <PAMRasterBand band="184">
    <Metadata>
      <MDI key="STATISTICS_MAXIMUM">299.35582567887</MDI>
      <MDI key="STATISTICS_MEAN">-9999</MDI>
      <MDI key="STATISTICS_MINIMUM">15.830246371654</MDI>
      <MDI key="STATISTICS_STDDEV">-9999</MDI>
    </Metadata>
  </PAMRasterBand>
  <PAMRasterBand band="185">
    <Metadata>
      <MDI key="STATISTICS_MAXIMUM">118.11662166403</MDI>
      <MDI key="STATISTICS_MEAN">-9999</MDI>
      <MDI key="STATISTICS_MINIMUM">-13.130274680055</MDI>
      <MDI key="STATISTICS_STDDEV">-9999</MDI>
    </Metadata>
  </PAMRasterBand>
  <PAMRasterBand band="186">
    <Metadata>
      <MDI key="STATISTICS_MAXIMUM">50.220033514451</MDI>
      <MDI key="STATISTICS_MEAN">-9999</MDI>
      <MDI key="STATISTICS_MINIMUM">-12.901932108948</MDI>
      <MDI key="STATISTICS_STDDEV">-9999</MDI>
    </Metadata>
  </PAMRasterBand>
  <PAMRasterBand band="187">
    <Metadata>
      <MDI key="STATISTICS_MAXIMUM">44.127841055586</MDI>
      <MDI key="STATISTICS_MEAN">-9999</MDI>
      <MDI key="STATISTICS_MINIMUM">-9.6269392399272</MDI>
      <MDI key="STATISTICS_STDDEV">-9999</MDI>
    </Metadata>
  </PAMRasterBand>
  <PAMRasterBand band="188">
    <Metadata>
      <MDI key="STATISTICS_MAXIMUM">32.927568012824</MDI>
      <MDI key="STATISTICS_MEAN">-9999</MDI>
      <MDI key="STATISTICS_MINIMUM">-2.6766607715445</MDI>
      <MDI key="STATISTICS_STDDEV">-9999</MDI>
    </Metadata>
  </PAMRasterBand>
  <PAMRasterBand band="189">
    <Metadata>
      <MDI key="STATISTICS_MAXIMUM">110.06823401181</MDI>
      <MDI key="STATISTICS_MEAN">-9999</MDI>
      <MDI key="STATISTICS_MINIMUM">-11.477026405737</MDI>
      <MDI key="STATISTICS_STDDEV">-9999</MDI>
    </Metadata>
  </PAMRasterBand>
  <PAMRasterBand band="190">
    <Metadata>
      <MDI key="STATISTICS_MAXIMUM">117.05646608377</MDI>
      <MDI key="STATISTICS_MEAN">-9999</MDI>
      <MDI key="STATISTICS_MINIMUM">-11.374197873083</MDI>
      <MDI key="STATISTICS_STDDEV">-9999</MDI>
    </Metadata>
  </PAMRasterBand>
  <PAMRasterBand band="191">
    <Metadata>
      <MDI key="STATISTICS_MAXIMUM">117.398905501</MDI>
      <MDI key="STATISTICS_MEAN">-9999</MDI>
      <MDI key="STATISTICS_MINIMUM">-2.8767251899987</MDI>
      <MDI key="STATISTICS_STDDEV">-9999</MDI>
    </Metadata>
  </PAMRasterBand>
  <PAMRasterBand band="192">
    <Metadata>
      <MDI key="STATISTICS_MAXIMUM">178.27931099605</MDI>
      <MDI key="STATISTICS_MEAN">-9999</MDI>
      <MDI key="STATISTICS_MINIMUM">-27.118654629259</MDI>
      <MDI key="STATISTICS_STDDEV">-9999</MDI>
    </Metadata>
  </PAMRasterBand>
  <PAMRasterBand band="193">
    <Metadata>
      <MDI key="STATISTICS_MAXIMUM">254.36387993691</MDI>
      <MDI key="STATISTICS_MEAN">-9999</MDI>
      <MDI key="STATISTICS_MINIMUM">1.2339609601377</MDI>
      <MDI key="STATISTICS_STDDEV">-9999</MDI>
    </Metadata>
  </PAMRasterBand>
  <PAMRasterBand band="194">
    <Metadata>
      <MDI key="STATISTICS_MAXIMUM">236.31542778583</MDI>
      <MDI key="STATISTICS_MEAN">-9999</MDI>
      <MDI key="STATISTICS_MINIMUM">4.4617648942017</MDI>
      <MDI key="STATISTICS_STDDEV">-9999</MDI>
    </Metadata>
  </PAMRasterBand>
  <PAMRasterBand band="195">
    <Metadata>
      <MDI key="STATISTICS_MAXIMUM">286.06718558927</MDI>
      <MDI key="STATISTICS_MEAN">-9999</MDI>
      <MDI key="STATISTICS_MINIMUM">-9.358156000722</MDI>
      <MDI key="STATISTICS_STDDEV">-9999</MDI>
    </Metadata>
  </PAMRasterBand>
  <PAMRasterBand band="196">
    <Metadata>
      <MDI key="STATISTICS_MAXIMUM">317.640204498</MDI>
      <MDI key="STATISTICS_MEAN">-9999</MDI>
      <MDI key="STATISTICS_MINIMUM">41.765379018916</MDI>
      <MDI key="STATISTICS_STDDEV">-9999</MDI>
    </Metadata>
  </PAMRasterBand>
  <PAMRasterBand band="197">
    <Metadata>
      <MDI key="STATISTICS_MAXIMUM">59.940470240141</MDI>
      <MDI key="STATISTICS_MEAN">-9999</MDI>
      <MDI key="STATISTICS_MINIMUM">-6.7890056952883</MDI>
      <MDI key="STATISTICS_STDDEV">-9999</MDI>
    </Metadata>
  </PAMRasterBand>
  <PAMRasterBand band="198">
    <Metadata>
      <MDI key="STATISTICS_MAXIMUM">16.469047425972</MDI>
      <MDI key="STATISTICS_MEAN">-9999</MDI>
      <MDI key="STATISTICS_MINIMUM">-1.2332291855775</MDI>
      <MDI key="STATISTICS_STDDEV">-9999</MDI>
    </Metadata>
  </PAMRasterBand>
  <PAMRasterBand band="199">
    <Metadata>
      <MDI key="STATISTICS_MAXIMUM">58.44680769487</MDI>
      <MDI key="STATISTICS_MEAN">-9999</MDI>
      <MDI key="STATISTICS_MINIMUM">-14.784109574106</MDI>
      <MDI key="STATISTICS_STDDEV">-9999</MDI>
    </Metadata>
  </PAMRasterBand>
  <PAMRasterBand band="200">
    <Metadata>
      <MDI key="STATISTICS_MAXIMUM">17.660006245722</MDI>
      <MDI key="STATISTICS_MEAN">-9999</MDI>
      <MDI key="STATISTICS_MINIMUM">-3.2700918779433</MDI>
      <MDI key="STATISTICS_STDDEV">-9999</MDI>
    </Metadata>
  </PAMRasterBand>
  <PAMRasterBand band="201">
    <Metadata>
      <MDI key="STATISTICS_MAXIMUM">167.53012547577</MDI>
      <MDI key="STATISTICS_MEAN">-9999</MDI>
      <MDI key="STATISTICS_MINIMUM">-19.320330554463</MDI>
      <MDI key="STATISTICS_STDDEV">-9999</MDI>
    </Metadata>
  </PAMRasterBand>
  <PAMRasterBand band="202">
    <Metadata>
      <MDI key="STATISTICS_MAXIMUM">162.57864691734</MDI>
      <MDI key="STATISTICS_MEAN">-9999</MDI>
      <MDI key="STATISTICS_MINIMUM">-20.855613291753</MDI>
      <MDI key="STATISTICS_STDDEV">-9999</MDI>
    </Metadata>
  </PAMRasterBand>
  <PAMRasterBand band="203">
    <Metadata>
      <MDI key="STATISTICS_MAXIMUM">116.21731271056</MDI>
      <MDI key="STATISTICS_MEAN">-9999</MDI>
      <MDI key="STATISTICS_MINIMUM">-14.512961671451</MDI>
      <MDI key="STATISTICS_STDDEV">-9999</MDI>
    </Metadata>
  </PAMRasterBand>
  <PAMRasterBand band="204">
    <Metadata>
      <MDI key="STATISTICS_MAXIMUM">283.96457212462</MDI>
      <MDI key="STATISTICS_MEAN">-9999</MDI>
      <MDI key="STATISTICS_MINIMUM">-6.355518426527</MDI>
      <MDI key="STATISTICS_STDDEV">-9999</MDI>
    </Metadata>
  </PAMRasterBand>
  <PAMRasterBand band="205">
    <Metadata>
      <MDI key="STATISTICS_MAXIMUM">481.18984344605</MDI>
      <MDI key="STATISTICS_MEAN">-9999</MDI>
      <MDI key="STATISTICS_MINIMUM">7.1696561217272</MDI>
      <MDI key="STATISTICS_STDDEV">-9999</MDI>
    </Metadata>
  </PAMRasterBand>
  <PAMRasterBand band="206">
    <Metadata>
      <MDI key="STATISTICS_MAXIMUM">374.02368378678</MDI>
      <MDI key="STATISTICS_MEAN">-9999</MDI>
      <MDI key="STATISTICS_MINIMUM">87.441286668775</MDI>
      <MDI key="STATISTICS_STDDEV">-9999</MDI>
    </Metadata>
  </PAMRasterBand>
  <PAMRasterBand band="207">
    <Metadata>
      <MDI key="STATISTICS_MAXIMUM">344.08541141939</MDI>
      <MDI key="STATISTICS_MEAN">-9999</MDI>
      <MDI key="STATISTICS_MINIMUM">75.071644118508</MDI>
      <MDI key="STATISTICS_STDDEV">-9999</MDI>
    </Metadata>
  </PAMRasterBand>
  <PAMRasterBand band="208">
    <Metadata>
      <MDI key="STATISTICS_MAXIMUM">364.69832705961</MDI>
      <MDI key="STATISTICS_MEAN">-9999</MDI>
      <MDI key="STATISTICS_MINIMUM">-26.078378811114</MDI>
      <MDI key="STATISTICS_STDDEV">-9999</MDI>
    </Metadata>
  </PAMRasterBand>
  <PAMRasterBand band="209">
    <Metadata>
      <MDI key="STATISTICS_MAXIMUM">123.38827877873</MDI>
      <MDI key="STATISTICS_MEAN">-9999</MDI>
      <MDI key="STATISTICS_MINIMUM">-8.2097082199401</MDI>
      <MDI key="STATISTICS_STDDEV">-9999</MDI>
    </Metadata>
  </PAMRasterBand>
  <PAMRasterBand band="210">
    <Metadata>
      <MDI key="STATISTICS_MAXIMUM">38.273453781908</MDI>
      <MDI key="STATISTICS_MEAN">-9999</MDI>
      <MDI key="STATISTICS_MINIMUM">-2.8367103889561</MDI>
      <MDI key="STATISTICS_STDDEV">-9999</MDI>
    </Metadata>
  </PAMRasterBand>
  <PAMRasterBand band="211">
    <Metadata>
      <MDI key="STATISTICS_MAXIMUM">14.529628848612</MDI>
      <MDI key="STATISTICS_MEAN">-9999</MDI>
      <MDI key="STATISTICS_MINIMUM">-0.31673790076606</MDI>
      <MDI key="STATISTICS_STDDEV">-9999</MDI>
    </Metadata>
  </PAMRasterBand>
  <PAMRasterBand band="212">
    <Metadata>
      <MDI key="STATISTICS_MAXIMUM">44.682441542358</MDI>
      <MDI key="STATISTICS_MEAN">-9999</MDI>
      <MDI key="STATISTICS_MINIMUM">-4.0729544587439</MDI>
      <MDI key="STATISTICS_STDDEV">-9999</MDI>
    </Metadata>
  </PAMRasterBand>
  <PAMRasterBand band="213">
    <Metadata>
      <MDI key="STATISTICS_MAXIMUM">38.25874635163</MDI>
      <MDI key="STATISTICS_MEAN">-9999</MDI>
      <MDI key="STATISTICS_MINIMUM">-4.8770165034347</MDI>
      <MDI key="STATISTICS_STDDEV">-9999</MDI>
    </Metadata>
  </PAMRasterBand>
  <PAMRasterBand band="214">
    <Metadata>
      <MDI key="STATISTICS_MAXIMUM">203.4250427532</MDI>
      <MDI key="STATISTICS_MEAN">-9999</MDI>
      <MDI key="STATISTICS_MINIMUM">-10.670912798878</MDI>
      <MDI key="STATISTICS_STDDEV">-9999</MDI>
    </Metadata>
  </PAMRasterBand>
  <PAMRasterBand band="215">
    <Metadata>
      <MDI key="STATISTICS_MAXIMUM">230.13350992125</MDI>
      <MDI key="STATISTICS_MEAN">-9999</MDI>
      <MDI key="STATISTICS_MINIMUM">-26.868569156338</MDI>
      <MDI key="STATISTICS_STDDEV">-9999</MDI>
    </Metadata>
  </PAMRasterBand>
  <PAMRasterBand band="216">
    <Metadata>
      <MDI key="STATISTICS_MAXIMUM">129.05849711625</MDI>
      <MDI key="STATISTICS_MEAN">-9999</MDI>
      <MDI key="STATISTICS_MINIMUM">0.75218110899477</MDI>
      <MDI key="STATISTICS_STDDEV">-9999</MDI>
    </Metadata>
  </PAMRasterBand>
  <PAMRasterBand band="217">
    <Metadata>
      <MDI key="STATISTICS_MAXIMUM">180.53126762835</MDI>
      <MDI key="STATISTICS_MEAN">-9999</MDI>
      <MDI key="STATISTICS_MINIMUM">4.3659130796956</MDI>
      <MDI key="STATISTICS_STDDEV">-9999</MDI>
    </Metadata>
  </PAMRasterBand>
  <PAMRasterBand band="218">
    <Metadata>
      <MDI key="STATISTICS_MAXIMUM">318.4177502153</MDI>
      <MDI key="STATISTICS_MEAN">-9999</MDI>
      <MDI key="STATISTICS_MINIMUM">21.893814079614</MDI>
      <MDI key="STATISTICS_STDDEV">-9999</MDI>
    </Metadata>
  </PAMRasterBand>
  <PAMRasterBand band="219">
    <Metadata>
      <MDI key="STATISTICS_MAXIMUM">476.8842306298</MDI>
      <MDI key="STATISTICS_MEAN">-9999</MDI>
      <MDI key="STATISTICS_MINIMUM">121.16682874393</MDI>
      <MDI key="STATISTICS_STDDEV">-9999</MDI>
    </Metadata>
  </PAMRasterBand>
  <PAMRasterBand band="220">
    <Metadata>
      <MDI key="STATISTICS_MAXIMUM">190.28632069789</MDI>
      <MDI key="STATISTICS_MEAN">-9999</MDI>
      <MDI key="STATISTICS_MINIMUM">-7.1172193668507</MDI>
      <MDI key="STATISTICS_STDDEV">-9999</MDI>
    </Metadata>
  </PAMRasterBand>
  <PAMRasterBand band="221">
    <Metadata>
      <MDI key="STATISTICS_MAXIMUM">276.38439437933</MDI>
      <MDI key="STATISTICS_MEAN">-9999</MDI>
      <MDI key="STATISTICS_MINIMUM">-66.278794341636</MDI>
      <MDI key="STATISTICS_STDDEV">-9999</MDI>
    </Metadata>
  </PAMRasterBand>
  <PAMRasterBand band="222">
    <Metadata>
      <MDI key="STATISTICS_MAXIMUM">41.276064321037</MDI>
      <MDI key="STATISTICS_MEAN">-9999</MDI>
      <MDI key="STATISTICS_MINIMUM">-4.5668226995396</MDI>
      <MDI key="STATISTICS_STDDEV">-9999</MDI>
    </Metadata>
  </PAMRasterBand>
  <PAMRasterBand band="223">
    <Metadata>
      <MDI key="STATISTICS_MAXIMUM">20.911806870303</MDI>
      <MDI key="STATISTICS_MEAN">-9999</MDI>
      <MDI key="STATISTICS_MINIMUM">-2.6592810093261</MDI>
      <MDI key="STATISTICS_STDDEV">-9999</MDI>
    </Metadata>
  </PAMRasterBand>
  <PAMRasterBand band="224">
    <Metadata>
      <MDI key="STATISTICS_MAXIMUM">63.941135833614</MDI>
      <MDI key="STATISTICS_MEAN">-9999</MDI>
      <MDI key="STATISTICS_MINIMUM">-7.4975989545074</MDI>
      <MDI key="STATISTICS_STDDEV">-9999</MDI>
    </Metadata>
  </PAMRasterBand>
  <PAMRasterBand band="225">
    <Metadata>
      <MDI key="STATISTICS_MAXIMUM">50.002845300924</MDI>
      <MDI key="STATISTICS_MEAN">-9999</MDI>
      <MDI key="STATISTICS_MINIMUM">-6.1850114117394</MDI>
      <MDI key="STATISTICS_STDDEV">-9999</MDI>
    </Metadata>
  </PAMRasterBand>
  <PAMRasterBand band="226">
    <Metadata>
      <MDI key="STATISTICS_MAXIMUM">271.43261664688</MDI>
      <MDI key="STATISTICS_MEAN">-9999</MDI>
      <MDI key="STATISTICS_MINIMUM">-3.8883051104679</MDI>
      <MDI key="STATISTICS_STDDEV">-9999</MDI>
    </Metadata>
  </PAMRasterBand>
  <PAMRasterBand band="227">
    <Metadata>
      <MDI key="STATISTICS_MAXIMUM">54.222928647599</MDI>
      <MDI key="STATISTICS_MEAN">-9999</MDI>
      <MDI key="STATISTICS_MINIMUM">-6.470323749539</MDI>
      <MDI key="STATISTICS_STDDEV">-9999</MDI>
    </Metadata>
  </PAMRasterBand>
  <PAMRasterBand band="228">
    <Metadata>
      <MDI key="STATISTICS_MAXIMUM">237.76026408777</MDI>
      <MDI key="STATISTICS_MEAN">-9999</MDI>
      <MDI key="STATISTICS_MINIMUM">-16.289990652936</MDI>
      <MDI key="STATISTICS_STDDEV">-9999</MDI>
    </Metadata>
  </PAMRasterBand>
  <PAMRasterBand band="229">
    <Metadata>
      <MDI key="STATISTICS_MAXIMUM">243.53630565289</MDI>
      <MDI key="STATISTICS_MEAN">-9999</MDI>
      <MDI key="STATISTICS_MINIMUM">-5.0203057930847</MDI>
      <MDI key="STATISTICS_STDDEV">-9999</MDI>
    </Metadata>
  </PAMRasterBand>
  <PAMRasterBand band="230">
    <Metadata>
      <MDI key="STATISTICS_MAXIMUM">359.1846275199</MDI>
      <MDI key="STATISTICS_MEAN">-9999</MDI>
      <MDI key="STATISTICS_MINIMUM">2.8038620630725</MDI>
      <MDI key="STATISTICS_STDDEV">-9999</MDI>
    </Metadata>
  </PAMRasterBand>
  <PAMRasterBand band="231">
    <Metadata>
      <MDI key="STATISTICS_MAXIMUM">463.99030474974</MDI>
      <MDI key="STATISTICS_MEAN">-9999</MDI>
      <MDI key="STATISTICS_MINIMUM">16.323952450501</MDI>
      <MDI key="STATISTICS_STDDEV">-9999</MDI>
    </Metadata>
  </PAMRasterBand>
  <PAMRasterBand band="232">
    <Metadata>
      <MDI key="STATISTICS_MAXIMUM">150.02307516888</MDI>
      <MDI key="STATISTICS_MEAN">-9999</MDI>
      <MDI key="STATISTICS_MINIMUM">-7.3529683665155</MDI>
      <MDI key="STATISTICS_STDDEV">-9999</MDI>
    </Metadata>
  </PAMRasterBand>
  <PAMRasterBand band="233">
    <Metadata>
      <MDI key="STATISTICS_MAXIMUM">188.73923255906</MDI>
      <MDI key="STATISTICS_MEAN">-9999</MDI>
      <MDI key="STATISTICS_MINIMUM">-5.5969380688214</MDI>
      <MDI key="STATISTICS_STDDEV">-9999</MDI>
    </Metadata>
  </PAMRasterBand>
  <PAMRasterBand band="234">
    <Metadata>
      <MDI key="STATISTICS_MAXIMUM">33.641404038002</MDI>
      <MDI key="STATISTICS_MEAN">-9999</MDI>
      <MDI key="STATISTICS_MINIMUM">-9.6147987781078</MDI>
      <MDI key="STATISTICS_STDDEV">-9999</MDI>
    </Metadata>
  </PAMRasterBand>
  <PAMRasterBand band="235">
    <Metadata>
      <MDI key="STATISTICS_MAXIMUM">51.811761144155</MDI>
      <MDI key="STATISTICS_MEAN">-9999</MDI>
      <MDI key="STATISTICS_MINIMUM">-2.8160647556257</MDI>
      <MDI key="STATISTICS_STDDEV">-9999</MDI>
    </Metadata>
  </PAMRasterBand>
  <PAMRasterBand band="236">
    <Metadata>
      <MDI key="STATISTICS_MAXIMUM">41.931938006184</MDI>
      <MDI key="STATISTICS_MEAN">-9999</MDI>
      <MDI key="STATISTICS_MINIMUM">-5.5833840696596</MDI>
      <MDI key="STATISTICS_STDDEV">-9999</MDI>
    </Metadata>
  </PAMRasterBand>
  <PAMRasterBand band="237">
    <Metadata>
      <MDI key="STATISTICS_MAXIMUM">125.98546234909</MDI>
      <MDI key="STATISTICS_MEAN">-9999</MDI>
      <MDI key="STATISTICS_MINIMUM">-6.9412263981766</MDI>
      <MDI key="STATISTICS_STDDEV">-9999</MDI>
    </Metadata>
  </PAMRasterBand>
  <PAMRasterBand band="238">
    <Metadata>
      <MDI key="STATISTICS_MAXIMUM">126.27581979754</MDI>
      <MDI key="STATISTICS_MEAN">-9999</MDI>
      <MDI key="STATISTICS_MINIMUM">-13.750419856317</MDI>
      <MDI key="STATISTICS_STDDEV">-9999</MDI>
    </Metadata>
  </PAMRasterBand>
  <PAMRasterBand band="239">
    <Metadata>
      <MDI key="STATISTICS_MAXIMUM">169.2175751503</MDI>
      <MDI key="STATISTICS_MEAN">-9999</MDI>
      <MDI key="STATISTICS_MINIMUM">-5.8507952720345</MDI>
      <MDI key="STATISTICS_STDDEV">-9999</MDI>
    </Metadata>
  </PAMRasterBand>
  <PAMRasterBand band="240">
    <Metadata>
      <MDI key="STATISTICS_MAXIMUM">212.05377621302</MDI>
      <MDI key="STATISTICS_MEAN">-9999</MDI>
      <MDI key="STATISTICS_MINIMUM">5.1384767594732</MDI>
      <MDI key="STATISTICS_STDDEV">-9999</MDI>
    </Metadata>
  </PAMRasterBand>
  <PAMRasterBand band="241">
    <Metadata>
      <MDI key="STATISTICS_MAXIMUM">371.26285768872</MDI>
      <MDI key="STATISTICS_MEAN">-9999</MDI>
      <MDI key="STATISTICS_MINIMUM">4.3699408668143</MDI>
      <MDI key="STATISTICS_STDDEV">-9999</MDI>
    </Metadata>
  </PAMRasterBand>
  <PAMRasterBand band="242">
    <Metadata>
      <MDI key="STATISTICS_MAXIMUM">158.41994228802</MDI>
      <MDI key="STATISTICS_MEAN">-9999</MDI>
      <MDI key="STATISTICS_MINIMUM">17.928977626369</MDI>
      <MDI key="STATISTICS_STDDEV">-9999</MDI>
    </Metadata>
  </PAMRasterBand>
  <PAMRasterBand band="243">
    <Metadata>
      <MDI key="STATISTICS_MAXIMUM">588.52367310241</MDI>
      <MDI key="STATISTICS_MEAN">-9999</MDI>
      <MDI key="STATISTICS_MINIMUM">42.216612783787</MDI>
      <MDI key="STATISTICS_STDDEV">-9999</MDI>
    </Metadata>
  </PAMRasterBand>
  <PAMRasterBand band="244">
    <Metadata>
      <MDI key="STATISTICS_MAXIMUM">160.19080725959</MDI>
      <MDI key="STATISTICS_MEAN">-9999</MDI>
      <MDI key="STATISTICS_MINIMUM">27.169522656374</MDI>
      <MDI key="STATISTICS_STDDEV">-9999</MDI>
    </Metadata>
  </PAMRasterBand>
  <PAMRasterBand band="245">
    <Metadata>
      <MDI key="STATISTICS_MAXIMUM">157.5581518814</MDI>
      <MDI key="STATISTICS_MEAN">-9999</MDI>
      <MDI key="STATISTICS_MINIMUM">3.8529907084574</MDI>
      <MDI key="STATISTICS_STDDEV">-9999</MDI>
    </Metadata>
  </PAMRasterBand>
  <PAMRasterBand band="246">
    <Metadata>
      <MDI key="STATISTICS_MAXIMUM">13.239327851393</MDI>
      <MDI key="STATISTICS_MEAN">-9999</MDI>
      <MDI key="STATISTICS_MINIMUM">-1.5500112853271</MDI>
      <MDI key="STATISTICS_STDDEV">-9999</MDI>
    </Metadata>
  </PAMRasterBand>
  <PAMRasterBand band="247">
    <Metadata>
      <MDI key="STATISTICS_MAXIMUM">50.388286072939</MDI>
      <MDI key="STATISTICS_MEAN">-9999</MDI>
      <MDI key="STATISTICS_MINIMUM">-6.590986640255</MDI>
      <MDI key="STATISTICS_STDDEV">-9999</MDI>
    </Metadata>
  </PAMRasterBand>
  <PAMRasterBand band="248">
    <Metadata>
      <MDI key="STATISTICS_MAXIMUM">8.0856878431303</MDI>
      <MDI key="STATISTICS_MEAN">-9999</MDI>
      <MDI key="STATISTICS_MINIMUM">-0.69183672974078</MDI>
      <MDI key="STATISTICS_STDDEV">-9999</MDI>
    </Metadata>
  </PAMRasterBand>
  <PAMRasterBand band="249">
    <Metadata>
      <MDI key="STATISTICS_MAXIMUM">51.006755492836</MDI>
      <MDI key="STATISTICS_MEAN">-9999</MDI>
      <MDI key="STATISTICS_MINIMUM">-9.9256311464635</MDI>
      <MDI key="STATISTICS_STDDEV">-9999</MDI>
    </Metadata>
  </PAMRasterBand>
  <PAMRasterBand band="250">
    <Metadata>
      <MDI key="STATISTICS_MAXIMUM">162.30863382916</MDI>
      <MDI key="STATISTICS_MEAN">-9999</MDI>
      <MDI key="STATISTICS_MINIMUM">-18.118432808326</MDI>
      <MDI key="STATISTICS_STDDEV">-9999</MDI>
    </Metadata>
  </PAMRasterBand>
  <PAMRasterBand band="251">
    <Metadata>
      <MDI key="STATISTICS_MAXIMUM">197.655214035</MDI>
      <MDI key="STATISTICS_MEAN">-9999</MDI>
      <MDI key="STATISTICS_MINIMUM">-26.605372382108</MDI>
      <MDI key="STATISTICS_STDDEV">-9999</MDI>
    </Metadata>
  </PAMRasterBand>
  <PAMRasterBand band="252">
    <Metadata>
      <MDI key="STATISTICS_MAXIMUM">230.20153986057</MDI>
      <MDI key="STATISTICS_MEAN">-9999</MDI>
      <MDI key="STATISTICS_MINIMUM">-16.606233099966</MDI>
      <MDI key="STATISTICS_STDDEV">-9999</MDI>
    </Metadata>
  </PAMRasterBand>
  <PAMRasterBand band="253">
    <Metadata>
      <MDI key="STATISTICS_MAXIMUM">248.05230831356</MDI>
      <MDI key="STATISTICS_MEAN">-9999</MDI>
      <MDI key="STATISTICS_MINIMUM">0.40460463262217</MDI>
      <MDI key="STATISTICS_STDDEV">-9999</MDI>
    </Metadata>
  </PAMRasterBand>
  <PAMRasterBand band="254">
    <Metadata>
      <MDI key="STATISTICS_MAXIMUM">334.75392655246</MDI>
      <MDI key="STATISTICS_MEAN">-9999</MDI>
      <MDI key="STATISTICS_MINIMUM">15.345756737194</MDI>
      <MDI key="STATISTICS_STDDEV">-9999</MDI>
    </Metadata>
  </PAMRasterBand>
  <PAMRasterBand band="255">
    <Metadata>
      <MDI key="STATISTICS_MAXIMUM">274.56379340474</MDI>
      <MDI key="STATISTICS_MEAN">-9999</MDI>
      <MDI key="STATISTICS_MINIMUM">29.777165516825</MDI>
      <MDI key="STATISTICS_STDDEV">-9999</MDI>
    </Metadata>
  </PAMRasterBand>
  <PAMRasterBand band="256">
    <Metadata>
      <MDI key="STATISTICS_MAXIMUM">226.13897815374</MDI>
      <MDI key="STATISTICS_MEAN">-9999</MDI>
      <MDI key="STATISTICS_MINIMUM">14.876815059322</MDI>
      <MDI key="STATISTICS_STDDEV">-9999</MDI>
    </Metadata>
  </PAMRasterBand>
  <PAMRasterBand band="257">
    <Metadata>
      <MDI key="STATISTICS_MAXIMUM">54.154972474601</MDI>
      <MDI key="STATISTICS_MEAN">-9999</MDI>
      <MDI key="STATISTICS_MINIMUM">-4.8252101317117</MDI>
      <MDI key="STATISTICS_STDDEV">-9999</MDI>
    </Metadata>
  </PAMRasterBand>
  <PAMRasterBand band="258">
    <Metadata>
      <MDI key="STATISTICS_MAXIMUM">79.442822365667</MDI>
      <MDI key="STATISTICS_MEAN">-9999</MDI>
      <MDI key="STATISTICS_MINIMUM">-5.7881389735845</MDI>
      <MDI key="STATISTICS_STDDEV">-9999</MDI>
    </Metadata>
  </PAMRasterBand>
  <PAMRasterBand band="259">
    <Metadata>
      <MDI key="STATISTICS_MAXIMUM">24.406671017713</MDI>
      <MDI key="STATISTICS_MEAN">-9999</MDI>
      <MDI key="STATISTICS_MINIMUM">-3.8577910911285</MDI>
      <MDI key="STATISTICS_STDDEV">-9999</MDI>
    </Metadata>
  </PAMRasterBand>
  <PAMRasterBand band="260">
    <Metadata>
      <MDI key="STATISTICS_MAXIMUM">59.438173459307</MDI>
      <MDI key="STATISTICS_MEAN">-9999</MDI>
      <MDI key="STATISTICS_MINIMUM">-6.4021841761567</MDI>
      <MDI key="STATISTICS_STDDEV">-9999</MDI>
    </Metadata>
  </PAMRasterBand>
  <PAMRasterBand band="261">
    <Metadata>
      <MDI key="STATISTICS_MAXIMUM">110.31100897167</MDI>
      <MDI key="STATISTICS_MEAN">-9999</MDI>
      <MDI key="STATISTICS_MINIMUM">-25.059519834203</MDI>
      <MDI key="STATISTICS_STDDEV">-9999</MDI>
    </Metadata>
  </PAMRasterBand>
  <PAMRasterBand band="262">
    <Metadata>
      <MDI key="STATISTICS_MAXIMUM">160.62167546701</MDI>
      <MDI key="STATISTICS_MEAN">-9999</MDI>
      <MDI key="STATISTICS_MINIMUM">-20.31016702159</MDI>
      <MDI key="STATISTICS_STDDEV">-9999</MDI>
    </Metadata>
  </PAMRasterBand>
  <PAMRasterBand band="263">
    <Metadata>
      <MDI key="STATISTICS_MAXIMUM">67.028534491165</MDI>
      <MDI key="STATISTICS_MEAN">-9999</MDI>
      <MDI key="STATISTICS_MINIMUM">-5.429233073845</MDI>
      <MDI key="STATISTICS_STDDEV">-9999</MDI>
    </Metadata>
  </PAMRasterBand>
  <PAMRasterBand band="264">
    <Metadata>
      <MDI key="STATISTICS_MAXIMUM">197.73637097723</MDI>
      <MDI key="STATISTICS_MEAN">-9999</MDI>
      <MDI key="STATISTICS_MINIMUM">-35.369666751042</MDI>
      <MDI key="STATISTICS_STDDEV">-9999</MDI>
    </Metadata>
  </PAMRasterBand>
  <PAMRasterBand band="265">
    <Metadata>
      <MDI key="STATISTICS_MAXIMUM">296.38801615076</MDI>
      <MDI key="STATISTICS_MEAN">-9999</MDI>
      <MDI key="STATISTICS_MINIMUM">36.112520308364</MDI>
      <MDI key="STATISTICS_STDDEV">-9999</MDI>
    </Metadata>
  </PAMRasterBand>
  <PAMRasterBand band="266">
    <Metadata>
      <MDI key="STATISTICS_MAXIMUM">495.07958380346</MDI>
      <MDI key="STATISTICS_MEAN">-9999</MDI>
      <MDI key="STATISTICS_MINIMUM">41.909688742523</MDI>
      <MDI key="STATISTICS_STDDEV">-9999</MDI>
    </Metadata>
  </PAMRasterBand>
  <PAMRasterBand band="267">
    <Metadata>
      <MDI key="STATISTICS_MAXIMUM">939.91959250008</MDI>
      <MDI key="STATISTICS_MEAN">-9999</MDI>
      <MDI key="STATISTICS_MINIMUM">144.14572454595</MDI>
      <MDI key="STATISTICS_STDDEV">-9999</MDI>
    </Metadata>
  </PAMRasterBand>
  <PAMRasterBand band="268">
    <Metadata>
      <MDI key="STATISTICS_MAXIMUM">207.63679106211</MDI>
      <MDI key="STATISTICS_MEAN">-9999</MDI>
      <MDI key="STATISTICS_MINIMUM">12.826440543545</MDI>
      <MDI key="STATISTICS_STDDEV">-9999</MDI>
    </Metadata>
  </PAMRasterBand>
  <PAMRasterBand band="269">
    <Metadata>
      <MDI key="STATISTICS_MAXIMUM">192.28552594054</MDI>
      <MDI key="STATISTICS_MEAN">-9999</MDI>
      <MDI key="STATISTICS_MINIMUM">-18.457241747044</MDI>
      <MDI key="STATISTICS_STDDEV">-9999</MDI>
    </Metadata>
  </PAMRasterBand>
  <PAMRasterBand band="270">
    <Metadata>
      <MDI key="STATISTICS_MAXIMUM">73.988708729536</MDI>
      <MDI key="STATISTICS_MEAN">-9999</MDI>
      <MDI key="STATISTICS_MINIMUM">-3.0956273880457</MDI>
      <MDI key="STATISTICS_STDDEV">-9999</MDI>
    </Metadata>
  </PAMRasterBand>
  <PAMRasterBand band="271">
    <Metadata>
      <MDI key="STATISTICS_MAXIMUM">13.29269012678</MDI>
      <MDI key="STATISTICS_MEAN">-9999</MDI>
      <MDI key="STATISTICS_MINIMUM">-3.1421087872787</MDI>
      <MDI key="STATISTICS_STDDEV">-9999</MDI>
    </Metadata>
  </PAMRasterBand>
  <PAMRasterBand band="272">
    <Metadata>
      <MDI key="STATISTICS_MAXIMUM">89.815259816923</MDI>
      <MDI key="STATISTICS_MEAN">-9999</MDI>
      <MDI key="STATISTICS_MINIMUM">-5.7883578369389</MDI>
      <MDI key="STATISTICS_STDDEV">-9999</MDI>
    </Metadata>
  </PAMRasterBand>
  <PAMRasterBand band="273">
    <Metadata>
      <MDI key="STATISTICS_MAXIMUM">99.226465289219</MDI>
      <MDI key="STATISTICS_MEAN">-9999</MDI>
      <MDI key="STATISTICS_MINIMUM">-29.432932680866</MDI>
      <MDI key="STATISTICS_STDDEV">-9999</MDI>
    </Metadata>
  </PAMRasterBand>
  <PAMRasterBand band="274">
    <Metadata>
      <MDI key="STATISTICS_MAXIMUM">252.27912370643</MDI>
      <MDI key="STATISTICS_MEAN">-9999</MDI>
      <MDI key="STATISTICS_MINIMUM">-11.2222690746</MDI>
      <MDI key="STATISTICS_STDDEV">-9999</MDI>
    </Metadata>
  </PAMRasterBand>
  <PAMRasterBand band="275">
    <Metadata>
      <MDI key="STATISTICS_MAXIMUM">97.664216221972</MDI>
      <MDI key="STATISTICS_MEAN">-9999</MDI>
      <MDI key="STATISTICS_MINIMUM">-12.066046290923</MDI>
      <MDI key="STATISTICS_STDDEV">-9999</MDI>
    </Metadata>
  </PAMRasterBand>
  <PAMRasterBand band="276">
    <Metadata>
      <MDI key="STATISTICS_MAXIMUM">228.06614393535</MDI>
      <MDI key="STATISTICS_MEAN">-9999</MDI>
      <MDI key="STATISTICS_MINIMUM">-59.997668951532</MDI>
      <MDI key="STATISTICS_STDDEV">-9999</MDI>
    </Metadata>
  </PAMRasterBand>
  <PAMRasterBand band="277">
    <Metadata>
      <MDI key="STATISTICS_MAXIMUM">266.38788996655</MDI>
      <MDI key="STATISTICS_MEAN">-9999</MDI>
      <MDI key="STATISTICS_MINIMUM">5.7138335342877</MDI>
      <MDI key="STATISTICS_STDDEV">-9999</MDI>
    </Metadata>
  </PAMRasterBand>
  <PAMRasterBand band="278">
    <Metadata>
      <MDI key="STATISTICS_MAXIMUM">229.35411056731</MDI>
      <MDI key="STATISTICS_MEAN">-9999</MDI>
      <MDI key="STATISTICS_MINIMUM">5.8186946488805</MDI>
      <MDI key="STATISTICS_STDDEV">-9999</MDI>
    </Metadata>
  </PAMRasterBand>
  <PAMRasterBand band="279">
    <Metadata>
      <MDI key="STATISTICS_MAXIMUM">266.07429894537</MDI>
      <MDI key="STATISTICS_MEAN">-9999</MDI>
      <MDI key="STATISTICS_MINIMUM">-7.1654693152902</MDI>
      <MDI key="STATISTICS_STDDEV">-9999</MDI>
    </Metadata>
  </PAMRasterBand>
  <PAMRasterBand band="280">
    <Metadata>
      <MDI key="STATISTICS_MAXIMUM">205.20761416822</MDI>
      <MDI key="STATISTICS_MEAN">-9999</MDI>
      <MDI key="STATISTICS_MINIMUM">35.141711455129</MDI>
      <MDI key="STATISTICS_STDDEV">-9999</MDI>
    </Metadata>
  </PAMRasterBand>
  <PAMRasterBand band="281">
    <Metadata>
      <MDI key="STATISTICS_MAXIMUM">169.94000963314</MDI>
      <MDI key="STATISTICS_MEAN">-9999</MDI>
      <MDI key="STATISTICS_MINIMUM">-13.861927445022</MDI>
      <MDI key="STATISTICS_STDDEV">-9999</MDI>
    </Metadata>
  </PAMRasterBand>
  <PAMRasterBand band="282">
    <Metadata>
      <MDI key="STATISTICS_MAXIMUM">41.163571749733</MDI>
      <MDI key="STATISTICS_MEAN">-9999</MDI>
      <MDI key="STATISTICS_MINIMUM">-5.6541999570233</MDI>
      <MDI key="STATISTICS_STDDEV">-9999</MDI>
    </Metadata>
  </PAMRasterBand>
  <PAMRasterBand band="283">
    <Metadata>
      <MDI key="STATISTICS_MAXIMUM">12.905050248276</MDI>
      <MDI key="STATISTICS_MEAN">-9999</MDI>
      <MDI key="STATISTICS_MINIMUM">-1.4616899021366</MDI>
      <MDI key="STATISTICS_STDDEV">-9999</MDI>
    </Metadata>
  </PAMRasterBand>
  <PAMRasterBand band="284">
    <Metadata>
      <MDI key="STATISTICS_MAXIMUM">6.2109733395727</MDI>
      <MDI key="STATISTICS_MEAN">-9999</MDI>
      <MDI key="STATISTICS_MINIMUM">-2.1302386643543</MDI>
      <MDI key="STATISTICS_STDDEV">-9999</MDI>
    </Metadata>
  </PAMRasterBand>
  <PAMRasterBand band="285">
    <Metadata>
      <MDI key="STATISTICS_MAXIMUM">73.109797279462</MDI>
      <MDI key="STATISTICS_MEAN">-9999</MDI>
      <MDI key="STATISTICS_MINIMUM">-13.68160024138</MDI>
      <MDI key="STATISTICS_STDDEV">-9999</MDI>
    </Metadata>
  </PAMRasterBand>
  <PAMRasterBand band="286">
    <Metadata>
      <MDI key="STATISTICS_MAXIMUM">177.02198273539</MDI>
      <MDI key="STATISTICS_MEAN">-9999</MDI>
      <MDI key="STATISTICS_MINIMUM">-30.343824332381</MDI>
      <MDI key="STATISTICS_STDDEV">-9999</MDI>
    </Metadata>
  </PAMRasterBand>
  <PAMRasterBand band="287">
    <Metadata>
      <MDI key="STATISTICS_MAXIMUM">272.89275668209</MDI>
      <MDI key="STATISTICS_MEAN">-9999</MDI>
      <MDI key="STATISTICS_MINIMUM">-41.179466086157</MDI>
      <MDI key="STATISTICS_STDDEV">-9999</MDI>
    </Metadata>
  </PAMRasterBand>
  <PAMRasterBand band="288">
    <Metadata>
      <MDI key="STATISTICS_MAXIMUM">199.14897959363</MDI>
      <MDI key="STATISTICS_MEAN">-9999</MDI>
      <MDI key="STATISTICS_MINIMUM">-2.5860122272475</MDI>
      <MDI key="STATISTICS_STDDEV">-9999</MDI>
    </Metadata>
  </PAMRasterBand>
  <PAMRasterBand band="289">
    <Metadata>
      <MDI key="STATISTICS_MAXIMUM">174.32671078904</MDI>
      <MDI key="STATISTICS_MEAN">-9999</MDI>
      <MDI key="STATISTICS_MINIMUM">7.2555167637092</MDI>
      <MDI key="STATISTICS_STDDEV">-9999</MDI>
    </Metadata>
  </PAMRasterBand>
  <PAMRasterBand band="290">
    <Metadata>
      <MDI key="STATISTICS_MAXIMUM">413.97296106157</MDI>
      <MDI key="STATISTICS_MEAN">-9999</MDI>
      <MDI key="STATISTICS_MINIMUM">100.89688349731</MDI>
      <MDI key="STATISTICS_STDDEV">-9999</MDI>
    </Metadata>
  </PAMRasterBand>
  <PAMRasterBand band="291">
    <Metadata>
      <MDI key="STATISTICS_MAXIMUM">374.75745203628</MDI>
      <MDI key="STATISTICS_MEAN">-9999</MDI>
      <MDI key="STATISTICS_MINIMUM">54.773257366152</MDI>
      <MDI key="STATISTICS_STDDEV">-9999</MDI>
    </Metadata>
  </PAMRasterBand>
  <PAMRasterBand band="292">
    <Metadata>
      <MDI key="STATISTICS_MAXIMUM">183.12719541012</MDI>
      <MDI key="STATISTICS_MEAN">-9999</MDI>
      <MDI key="STATISTICS_MINIMUM">24.86868462711</MDI>
      <MDI key="STATISTICS_STDDEV">-9999</MDI>
    </Metadata>
  </PAMRasterBand>
  <PAMRasterBand band="293">
    <Metadata>
      <MDI key="STATISTICS_MAXIMUM">116.0175723197</MDI>
      <MDI key="STATISTICS_MEAN">-9999</MDI>
      <MDI key="STATISTICS_MINIMUM">-23.285408241212</MDI>
      <MDI key="STATISTICS_STDDEV">-9999</MDI>
    </Metadata>
  </PAMRasterBand>
  <PAMRasterBand band="294">
    <Metadata>
      <MDI key="STATISTICS_MAXIMUM">28.108776825608</MDI>
      <MDI key="STATISTICS_MEAN">-9999</MDI>
      <MDI key="STATISTICS_MINIMUM">-6.5336757620703</MDI>
      <MDI key="STATISTICS_STDDEV">-9999</MDI>
    </Metadata>
  </PAMRasterBand>
  <PAMRasterBand band="295">
    <Metadata>
      <MDI key="STATISTICS_MAXIMUM">45.986321219563</MDI>
      <MDI key="STATISTICS_MEAN">-9999</MDI>
      <MDI key="STATISTICS_MINIMUM">-5.8882280554154</MDI>
      <MDI key="STATISTICS_STDDEV">-9999</MDI>
    </Metadata>
  </PAMRasterBand>
  <PAMRasterBand band="296">
    <Metadata>
      <MDI key="STATISTICS_MAXIMUM">0</MDI>
      <MDI key="STATISTICS_MEAN">-9999</MDI>
      <MDI key="STATISTICS_MINIMUM">0</MDI>
      <MDI key="STATISTICS_STDDEV">-9999</MDI>
    </Metadata>
  </PAMRasterBand>
  <PAMRasterBand band="297">
    <Metadata>
      <MDI key="STATISTICS_MAXIMUM">54.637282401635</MDI>
      <MDI key="STATISTICS_MEAN">-9999</MDI>
      <MDI key="STATISTICS_MINIMUM">-8.7517635641213</MDI>
      <MDI key="STATISTICS_STDDEV">-9999</MDI>
    </Metadata>
  </PAMRasterBand>
  <PAMRasterBand band="298">
    <Metadata>
      <MDI key="STATISTICS_MAXIMUM">246.41368863943</MDI>
      <MDI key="STATISTICS_MEAN">-9999</MDI>
      <MDI key="STATISTICS_MINIMUM">-47.914056635386</MDI>
      <MDI key="STATISTICS_STDDEV">-9999</MDI>
    </Metadata>
  </PAMRasterBand>
  <PAMRasterBand band="299">
    <Metadata>
      <MDI key="STATISTICS_MAXIMUM">246.72015228541</MDI>
      <MDI key="STATISTICS_MEAN">-9999</MDI>
      <MDI key="STATISTICS_MINIMUM">-27.010980533232</MDI>
      <MDI key="STATISTICS_STDDEV">-9999</MDI>
    </Metadata>
  </PAMRasterBand>
  <PAMRasterBand band="300">
    <Metadata>
      <MDI key="STATISTICS_MAXIMUM">316.98626245397</MDI>
      <MDI key="STATISTICS_MEAN">-9999</MDI>
      <MDI key="STATISTICS_MINIMUM">-8.4628899267353</MDI>
      <MDI key="STATISTICS_STDDEV">-9999</MDI>
    </Metadata>
  </PAMRasterBand>
</PAMDataset>
